{"v":"5.9.6","fr":30,"ip":0,"op":102,"w":1600,"h":1600,"nm":"Quote","ddd":0,"assets":[],"layers":[{"ddd":0,"ind":1,"ty":4,"nm":"@","parent":2,"sr":1,"ks":{"o":{"a":0,"k":100},"r":{"k":[{"s":[-22.36],"t":0,"i":{"x":[1],"y":[1]},"o":{"x":[0],"y":[0]}},{"s":[-21.408],"t":1,"i":{"x":[1],"y":[1]},"o":{"x":[0],"y":[0]}},{"s":[-20.399],"t":2,"i":{"x":[1],"y":[1]},"o":{"x":[0],"y":[0]}},{"s":[-19.335],"t":3,"i":{"x":[1],"y":[1]},"o":{"x":[0],"y":[0]}},{"s":[-18.221],"t":4,"i":{"x":[1],"y":[1]},"o":{"x":[0],"y":[0]}},{"s":[-17.062],"t":5,"i":{"x":[1],"y":[1]},"o":{"x":[0],"y":[0]}},{"s":[-15.861],"t":6,"i":{"x":[1],"y":[1]},"o":{"x":[0],"y":[0]}},{"s":[-14.623],"t":7,"i":{"x":[1],"y":[1]},"o":{"x":[0],"y":[0]}},{"s":[-13.354],"t":8,"i":{"x":[1],"y":[1]},"o":{"x":[0],"y":[0]}},{"s":[-12.059],"t":9,"i":{"x":[1],"y":[1]},"o":{"x":[0],"y":[0]}},{"s":[-10.743],"t":10,"i":{"x":[1],"y":[1]},"o":{"x":[0],"y":[0]}},{"s":[-9.411],"t":11,"i":{"x":[1],"y":[1]},"o":{"x":[0],"y":[0]}},{"s":[-8.07],"t":12,"i":{"x":[1],"y":[1]},"o":{"x":[0],"y":[0]}},{"s":[-6.726],"t":13,"i":{"x":[1],"y":[1]},"o":{"x":[0],"y":[0]}},{"s":[-5.385],"t":14,"i":{"x":[1],"y":[1]},"o":{"x":[0],"y":[0]}},{"s":[-4.054],"t":15,"i":{"x":[1],"y":[1]},"o":{"x":[0],"y":[0]}},{"s":[-2.74],"t":16,"i":{"x":[1],"y":[1]},"o":{"x":[0],"y":[0]}},{"s":[-1.449],"t":17,"i":{"x":[1],"y":[1]},"o":{"x":[0],"y":[0]}},{"s":[-0.189],"t":18,"i":{"x":[1],"y":[1]},"o":{"x":[0],"y":[0]}},{"s":[1.032],"t":19,"i":{"x":[1],"y":[1]},"o":{"x":[0],"y":[0]}},{"s":[2.216],"t":20,"i":{"x":[1],"y":[1]},"o":{"x":[0],"y":[0]}},{"s":[3.37],"t":21,"i":{"x":[1],"y":[1]},"o":{"x":[0],"y":[0]}},{"s":[4.492],"t":22,"i":{"x":[1],"y":[1]},"o":{"x":[0],"y":[0]}},{"s":[5.575],"t":23,"i":{"x":[1],"y":[1]},"o":{"x":[0],"y":[0]}},{"s":[6.616],"t":24,"i":{"x":[1],"y":[1]},"o":{"x":[0],"y":[0]}},{"s":[7.61],"t":25,"i":{"x":[1],"y":[1]},"o":{"x":[0],"y":[0]}},{"s":[8.55],"t":26,"i":{"x":[1],"y":[1]},"o":{"x":[0],"y":[0]}},{"s":[9.434],"t":27,"i":{"x":[1],"y":[1]},"o":{"x":[0],"y":[0]}},{"s":[10.256],"t":28,"i":{"x":[1],"y":[1]},"o":{"x":[0],"y":[0]}},{"s":[11.01],"t":29,"i":{"x":[1],"y":[1]},"o":{"x":[0],"y":[0]}},{"s":[11.693],"t":30,"i":{"x":[1],"y":[1]},"o":{"x":[0],"y":[0]}},{"s":[12.299],"t":31,"i":{"x":[1],"y":[1]},"o":{"x":[0],"y":[0]}},{"s":[12.823],"t":32,"i":{"x":[1],"y":[1]},"o":{"x":[0],"y":[0]}},{"s":[13.261],"t":33,"i":{"x":[1],"y":[1]},"o":{"x":[0],"y":[0]}},{"s":[13.609],"t":34,"i":{"x":[1],"y":[1]},"o":{"x":[0],"y":[0]}},{"s":[13.862],"t":35,"i":{"x":[1],"y":[1]},"o":{"x":[0],"y":[0]}},{"s":[14.016],"t":36,"i":{"x":[1],"y":[1]},"o":{"x":[0],"y":[0]}},{"s":[14.067],"t":37,"i":{"x":[1],"y":[1]},"o":{"x":[0],"y":[0]}},{"s":[14.034],"t":38,"i":{"x":[1],"y":[1]},"o":{"x":[0],"y":[0]}},{"s":[13.958],"t":39,"i":{"x":[1],"y":[1]},"o":{"x":[0],"y":[0]}},{"s":[13.842],"t":40,"i":{"x":[1],"y":[1]},"o":{"x":[0],"y":[0]}},{"s":[13.686],"t":41,"i":{"x":[1],"y":[1]},"o":{"x":[0],"y":[0]}},{"s":[13.491],"t":42,"i":{"x":[1],"y":[1]},"o":{"x":[0],"y":[0]}},{"s":[13.258],"t":43,"i":{"x":[1],"y":[1]},"o":{"x":[0],"y":[0]}},{"s":[12.987],"t":44,"i":{"x":[1],"y":[1]},"o":{"x":[0],"y":[0]}},{"s":[12.678],"t":45,"i":{"x":[1],"y":[1]},"o":{"x":[0],"y":[0]}},{"s":[12.333],"t":46,"i":{"x":[1],"y":[1]},"o":{"x":[0],"y":[0]}},{"s":[11.952],"t":47,"i":{"x":[1],"y":[1]},"o":{"x":[0],"y":[0]}},{"s":[11.534],"t":48,"i":{"x":[1],"y":[1]},"o":{"x":[0],"y":[0]}},{"s":[11.082],"t":49,"i":{"x":[1],"y":[1]},"o":{"x":[0],"y":[0]}},{"s":[10.593],"t":50,"i":{"x":[1],"y":[1]},"o":{"x":[0],"y":[0]}},{"s":[10.07],"t":51,"i":{"x":[1],"y":[1]},"o":{"x":[0],"y":[0]}},{"s":[9.513],"t":52,"i":{"x":[1],"y":[1]},"o":{"x":[0],"y":[0]}},{"s":[8.922],"t":53,"i":{"x":[1],"y":[1]},"o":{"x":[0],"y":[0]}},{"s":[8.297],"t":54,"i":{"x":[1],"y":[1]},"o":{"x":[0],"y":[0]}},{"s":[7.638],"t":55,"i":{"x":[1],"y":[1]},"o":{"x":[0],"y":[0]}},{"s":[6.947],"t":56,"i":{"x":[1],"y":[1]},"o":{"x":[0],"y":[0]}},{"s":[6.225],"t":57,"i":{"x":[1],"y":[1]},"o":{"x":[0],"y":[0]}},{"s":[5.47],"t":58,"i":{"x":[1],"y":[1]},"o":{"x":[0],"y":[0]}},{"s":[4.685],"t":59,"i":{"x":[1],"y":[1]},"o":{"x":[0],"y":[0]}},{"s":[3.87],"t":60,"i":{"x":[1],"y":[1]},"o":{"x":[0],"y":[0]}},{"s":[3.027],"t":61,"i":{"x":[1],"y":[1]},"o":{"x":[0],"y":[0]}},{"s":[2.155],"t":62,"i":{"x":[1],"y":[1]},"o":{"x":[0],"y":[0]}},{"s":[1.257],"t":63,"i":{"x":[1],"y":[1]},"o":{"x":[0],"y":[0]}},{"s":[0.334],"t":64,"i":{"x":[1],"y":[1]},"o":{"x":[0],"y":[0]}},{"s":[-0.613],"t":65,"i":{"x":[1],"y":[1]},"o":{"x":[0],"y":[0]}},{"s":[-1.583],"t":66,"i":{"x":[1],"y":[1]},"o":{"x":[0],"y":[0]}},{"s":[-2.572],"t":67,"i":{"x":[1],"y":[1]},"o":{"x":[0],"y":[0]}},{"s":[-3.58],"t":68,"i":{"x":[1],"y":[1]},"o":{"x":[0],"y":[0]}},{"s":[-4.604],"t":69,"i":{"x":[1],"y":[1]},"o":{"x":[0],"y":[0]}},{"s":[-5.642],"t":70,"i":{"x":[1],"y":[1]},"o":{"x":[0],"y":[0]}},{"s":[-6.691],"t":71,"i":{"x":[1],"y":[1]},"o":{"x":[0],"y":[0]}},{"s":[-7.749],"t":72,"i":{"x":[1],"y":[1]},"o":{"x":[0],"y":[0]}},{"s":[-8.812],"t":73,"i":{"x":[1],"y":[1]},"o":{"x":[0],"y":[0]}},{"s":[-9.876],"t":74,"i":{"x":[1],"y":[1]},"o":{"x":[0],"y":[0]}},{"s":[-10.939],"t":75,"i":{"x":[1],"y":[1]},"o":{"x":[0],"y":[0]}},{"s":[-11.997],"t":76,"i":{"x":[1],"y":[1]},"o":{"x":[0],"y":[0]}},{"s":[-13.045],"t":77,"i":{"x":[1],"y":[1]},"o":{"x":[0],"y":[0]}},{"s":[-14.079],"t":78,"i":{"x":[1],"y":[1]},"o":{"x":[0],"y":[0]}},{"s":[-15.095],"t":79,"i":{"x":[1],"y":[1]},"o":{"x":[0],"y":[0]}},{"s":[-16.082],"t":80,"i":{"x":[1],"y":[1]},"o":{"x":[0],"y":[0]}},{"s":[-17.027],"t":81,"i":{"x":[1],"y":[1]},"o":{"x":[0],"y":[0]}},{"s":[-17.927],"t":82,"i":{"x":[1],"y":[1]},"o":{"x":[0],"y":[0]}},{"s":[-18.779],"t":83,"i":{"x":[1],"y":[1]},"o":{"x":[0],"y":[0]}},{"s":[-19.578],"t":84,"i":{"x":[1],"y":[1]},"o":{"x":[0],"y":[0]}},{"s":[-20.322],"t":85,"i":{"x":[1],"y":[1]},"o":{"x":[0],"y":[0]}},{"s":[-21.007],"t":86,"i":{"x":[1],"y":[1]},"o":{"x":[0],"y":[0]}},{"s":[-21.632],"t":87,"i":{"x":[1],"y":[1]},"o":{"x":[0],"y":[0]}},{"s":[-22.193],"t":88,"i":{"x":[1],"y":[1]},"o":{"x":[0],"y":[0]}},{"s":[-22.687],"t":89,"i":{"x":[1],"y":[1]},"o":{"x":[0],"y":[0]}},{"s":[-23.113],"t":90,"i":{"x":[1],"y":[1]},"o":{"x":[0],"y":[0]}},{"s":[-23.469],"t":91,"i":{"x":[1],"y":[1]},"o":{"x":[0],"y":[0]}},{"s":[-23.752],"t":92,"i":{"x":[1],"y":[1]},"o":{"x":[0],"y":[0]}},{"s":[-23.96],"t":93,"i":{"x":[1],"y":[1]},"o":{"x":[0],"y":[0]}},{"s":[-24.094],"t":94,"i":{"x":[1],"y":[1]},"o":{"x":[0],"y":[0]}},{"s":[-24.15],"t":95,"i":{"x":[1],"y":[1]},"o":{"x":[0],"y":[0]}},{"s":[-24.129],"t":96,"i":{"x":[1],"y":[1]},"o":{"x":[0],"y":[0]}},{"s":[-24.03],"t":97,"i":{"x":[1],"y":[1]},"o":{"x":[0],"y":[0]}},{"s":[-23.853],"t":98,"i":{"x":[1],"y":[1]},"o":{"x":[0],"y":[0]}},{"s":[-23.598],"t":99,"i":{"x":[1],"y":[1]},"o":{"x":[0],"y":[0]}},{"s":[-23.264],"t":100,"i":{"x":[1],"y":[1]},"o":{"x":[0],"y":[0]}},{"s":[-22.852],"t":101,"i":{"x":[1],"y":[1]},"o":{"x":[0],"y":[0]}}]},"p":{"a":0,"k":[39.836,0.464,0]},"a":{"a":0,"k":[-266.068,-231.121,0]},"s":{"a":0,"k":[100,100,100]}},"ao":0,"shapes":[{"ty":"gr","it":[{"ind":0,"ty":"sh","ks":{"a":0,"k":{"i":[[6.874,-15.835],[-0.894,-6.663],[-6.093,-1.944],[-4.605,2.558],[-4.43,6.067],[0,0],[2.785,0.889],[7.694,-5.934]],"o":[[-4.569,11.01],[0.895,6.664],[4.09,1.305],[4.604,-2.559],[0,0],[-2.389,-1.529],[-9.749,-3.111],[-7.698,5.937]],"v":[[-288.628,-232.561],[-294.137,-206.052],[-283.656,-193.142],[-270.613,-195.021],[-257.063,-207.96],[-232.843,-265.827],[-240.604,-269.455],[-266.77,-265.218]],"c":true}},"nm":"Path 1","hd":false},{"ind":1,"ty":"sh","ks":{"a":0,"k":{"i":[[8.149,-22.235],[14.749,-10.158],[17.407,5.555],[4.498,4.839],[1.24,6.631],[14.362,4.583],[4.698,6.919],[0.026,9.984],[-4.799,11.128],[-15.626,9.592],[-16.537,-5.277],[-7.338,-8.862],[0,0],[0,0],[-9.836,-3.139],[-8.02,7.848],[-5.216,14.543],[8.478,20.161],[26.111,8.332],[15.633,-4.361],[12.485,-13.134],[7.289,-19.54],[-8.426,-20.477],[-27.156,-8.666],[-8.724,-0.914],[-5.859,0.623],[0,0],[9.689,0.741],[9.052,2.889],[13.503,14.329],[2.313,20.396],[-8.981,25.137],[-16.121,15.81],[-20.771,4.832],[-21.933,-6.999],[-13.027,-14.177],[-2.566,-19.614]],"o":[[-8.12,22.439],[-14.75,10.158],[-7.138,-2.278],[-4.498,-4.838],[-12.197,8.767],[-8.355,-2.666],[-4.698,-6.915],[-0.029,-9.982],[9.554,-20.925],[15.622,-9.591],[12.794,4.083],[0,0],[0,0],[-5.342,11.626],[7.396,2.36],[8.017,-7.846],[10.755,-28.598],[-8.48,-20.159],[-16.626,-5.305],[-15.633,4.362],[-12.488,13.134],[-11.115,30.02],[8.426,20.476],[7.311,2.333],[8.722,0.913],[0,0],[-6.421,1.786],[-9.689,-0.743],[-23.761,-7.582],[-13.505,-14.332],[-2.316,-20.398],[8.71,-23.69],[16.121,-15.808],[20.768,-4.832],[21.933,6.999],[13.025,14.178],[2.563,19.614]],"v":[[-153.321,-205.784],[-187.624,-156.888],[-235.86,-149.983],[-253.312,-160.659],[-261.919,-177.863],[-301.755,-171.586],[-321.335,-185.962],[-328.422,-211.311],[-321.266,-242.976],[-283.499,-288.752],[-235.258,-295.224],[-205.061,-275.806],[-198.585,-267.698],[-229.698,-193.186],[-222.956,-171.039],[-199.831,-179.268],[-179.98,-212.852],[-176.565,-285.989],[-228.452,-328.727],[-276.837,-330.142],[-319.016,-303.898],[-348.68,-254.888],[-352.712,-179.143],[-299.34,-135.428],[-275.288,-130.558],[-253.417,-130.124],[-255.502,-106.911],[-279.666,-105.343],[-307.778,-110.789],[-363.675,-143.658],[-387.403,-195.751],[-377.403,-264.054],[-340.156,-323.303],[-284.818,-354.265],[-220.763,-351.016],[-168.325,-319.25],[-144.941,-268.561]],"c":true}},"nm":"Path 2","hd":false},{"ty":"fl","c":{"a":0,"k":[0.007843137719,0.007843137719,0.007843137719,1]},"o":{"a":0,"k":100},"r":1,"bm":0,"nm":"Fill 1","hd":false},{"ty":"tr","p":{"a":0,"k":[0,0]},"a":{"a":0,"k":[0,0]},"s":{"a":0,"k":[100,100]},"r":{"a":0,"k":0},"o":{"a":0,"k":100},"sk":{"a":0,"k":0},"sa":{"a":0,"k":0},"nm":"Transform"}],"nm":"Group 1","bm":0,"hd":false}],"ip":0,"op":151,"st":0,"ct":1,"bm":0},{"ddd":0,"ind":2,"ty":4,"nm":"M 2","sr":1,"ks":{"o":{"a":0,"k":100},"r":{"k":[{"s":[2.921],"t":0,"i":{"x":[1],"y":[1]},"o":{"x":[0],"y":[0]}},{"s":[3.418],"t":1,"i":{"x":[1],"y":[1]},"o":{"x":[0],"y":[0]}},{"s":[3.887],"t":2,"i":{"x":[1],"y":[1]},"o":{"x":[0],"y":[0]}},{"s":[4.325],"t":3,"i":{"x":[1],"y":[1]},"o":{"x":[0],"y":[0]}},{"s":[4.728],"t":4,"i":{"x":[1],"y":[1]},"o":{"x":[0],"y":[0]}},{"s":[5.094],"t":5,"i":{"x":[1],"y":[1]},"o":{"x":[0],"y":[0]}},{"s":[5.419],"t":6,"i":{"x":[1],"y":[1]},"o":{"x":[0],"y":[0]}},{"s":[5.707],"t":7,"i":{"x":[1],"y":[1]},"o":{"x":[0],"y":[0]}},{"s":[5.983],"t":8,"i":{"x":[1],"y":[1]},"o":{"x":[0],"y":[0]}},{"s":[6.249],"t":9,"i":{"x":[1],"y":[1]},"o":{"x":[0],"y":[0]}},{"s":[6.503],"t":10,"i":{"x":[1],"y":[1]},"o":{"x":[0],"y":[0]}},{"s":[6.743],"t":11,"i":{"x":[1],"y":[1]},"o":{"x":[0],"y":[0]}},{"s":[6.967],"t":12,"i":{"x":[1],"y":[1]},"o":{"x":[0],"y":[0]}},{"s":[7.174],"t":13,"i":{"x":[1],"y":[1]},"o":{"x":[0],"y":[0]}},{"s":[7.362],"t":14,"i":{"x":[1],"y":[1]},"o":{"x":[0],"y":[0]}},{"s":[7.531],"t":15,"i":{"x":[1],"y":[1]},"o":{"x":[0],"y":[0]}},{"s":[7.679],"t":16,"i":{"x":[1],"y":[1]},"o":{"x":[0],"y":[0]}},{"s":[7.805],"t":17,"i":{"x":[1],"y":[1]},"o":{"x":[0],"y":[0]}},{"s":[7.909],"t":18,"i":{"x":[1],"y":[1]},"o":{"x":[0],"y":[0]}},{"s":[7.991],"t":19,"i":{"x":[1],"y":[1]},"o":{"x":[0],"y":[0]}},{"s":[8.049],"t":20,"i":{"x":[1],"y":[1]},"o":{"x":[0],"y":[0]}},{"s":[8.083],"t":21,"i":{"x":[1],"y":[1]},"o":{"x":[0],"y":[0]}},{"s":[8.093],"t":22,"i":{"x":[1],"y":[1]},"o":{"x":[0],"y":[0]}},{"s":[8.079],"t":23,"i":{"x":[1],"y":[1]},"o":{"x":[0],"y":[0]}},{"s":[8.041],"t":24,"i":{"x":[1],"y":[1]},"o":{"x":[0],"y":[0]}},{"s":[7.979],"t":25,"i":{"x":[1],"y":[1]},"o":{"x":[0],"y":[0]}},{"s":[7.892],"t":26,"i":{"x":[1],"y":[1]},"o":{"x":[0],"y":[0]}},{"s":[7.782],"t":27,"i":{"x":[1],"y":[1]},"o":{"x":[0],"y":[0]}},{"s":[7.648],"t":28,"i":{"x":[1],"y":[1]},"o":{"x":[0],"y":[0]}},{"s":[7.491],"t":29,"i":{"x":[1],"y":[1]},"o":{"x":[0],"y":[0]}},{"s":[7.31],"t":30,"i":{"x":[1],"y":[1]},"o":{"x":[0],"y":[0]}},{"s":[7.108],"t":31,"i":{"x":[1],"y":[1]},"o":{"x":[0],"y":[0]}},{"s":[6.883],"t":32,"i":{"x":[1],"y":[1]},"o":{"x":[0],"y":[0]}},{"s":[6.637],"t":33,"i":{"x":[1],"y":[1]},"o":{"x":[0],"y":[0]}},{"s":[6.37],"t":34,"i":{"x":[1],"y":[1]},"o":{"x":[0],"y":[0]}},{"s":[6.083],"t":35,"i":{"x":[1],"y":[1]},"o":{"x":[0],"y":[0]}},{"s":[5.777],"t":36,"i":{"x":[1],"y":[1]},"o":{"x":[0],"y":[0]}},{"s":[5.451],"t":37,"i":{"x":[1],"y":[1]},"o":{"x":[0],"y":[0]}},{"s":[5.107],"t":38,"i":{"x":[1],"y":[1]},"o":{"x":[0],"y":[0]}},{"s":[4.746],"t":39,"i":{"x":[1],"y":[1]},"o":{"x":[0],"y":[0]}},{"s":[4.368],"t":40,"i":{"x":[1],"y":[1]},"o":{"x":[0],"y":[0]}},{"s":[3.973],"t":41,"i":{"x":[1],"y":[1]},"o":{"x":[0],"y":[0]}},{"s":[3.563],"t":42,"i":{"x":[1],"y":[1]},"o":{"x":[0],"y":[0]}},{"s":[3.138],"t":43,"i":{"x":[1],"y":[1]},"o":{"x":[0],"y":[0]}},{"s":[2.698],"t":44,"i":{"x":[1],"y":[1]},"o":{"x":[0],"y":[0]}},{"s":[2.245],"t":45,"i":{"x":[1],"y":[1]},"o":{"x":[0],"y":[0]}},{"s":[1.778],"t":46,"i":{"x":[1],"y":[1]},"o":{"x":[0],"y":[0]}},{"s":[1.299],"t":47,"i":{"x":[1],"y":[1]},"o":{"x":[0],"y":[0]}},{"s":[0.807],"t":48,"i":{"x":[1],"y":[1]},"o":{"x":[0],"y":[0]}},{"s":[0.303],"t":49,"i":{"x":[1],"y":[1]},"o":{"x":[0],"y":[0]}},{"s":[-0.209],"t":50,"i":{"x":[1],"y":[1]},"o":{"x":[0],"y":[0]}},{"s":[-0.728],"t":51,"i":{"x":[1],"y":[1]},"o":{"x":[0],"y":[0]}},{"s":[-1.771],"t":53,"i":{"x":[1],"y":[1]},"o":{"x":[0],"y":[0]}},{"s":[-2.29],"t":54,"i":{"x":[1],"y":[1]},"o":{"x":[0],"y":[0]}},{"s":[-2.802],"t":55,"i":{"x":[1],"y":[1]},"o":{"x":[0],"y":[0]}},{"s":[-3.306],"t":56,"i":{"x":[1],"y":[1]},"o":{"x":[0],"y":[0]}},{"s":[-3.797],"t":57,"i":{"x":[1],"y":[1]},"o":{"x":[0],"y":[0]}},{"s":[-4.274],"t":58,"i":{"x":[1],"y":[1]},"o":{"x":[0],"y":[0]}},{"s":[-4.733],"t":59,"i":{"x":[1],"y":[1]},"o":{"x":[0],"y":[0]}},{"s":[-5.171],"t":60,"i":{"x":[1],"y":[1]},"o":{"x":[0],"y":[0]}},{"s":[-5.585],"t":61,"i":{"x":[1],"y":[1]},"o":{"x":[0],"y":[0]}},{"s":[-5.974],"t":62,"i":{"x":[1],"y":[1]},"o":{"x":[0],"y":[0]}},{"s":[-6.334],"t":63,"i":{"x":[1],"y":[1]},"o":{"x":[0],"y":[0]}},{"s":[-6.662],"t":64,"i":{"x":[1],"y":[1]},"o":{"x":[0],"y":[0]}},{"s":[-6.958],"t":65,"i":{"x":[1],"y":[1]},"o":{"x":[0],"y":[0]}},{"s":[-7.218],"t":66,"i":{"x":[1],"y":[1]},"o":{"x":[0],"y":[0]}},{"s":[-7.441],"t":67,"i":{"x":[1],"y":[1]},"o":{"x":[0],"y":[0]}},{"s":[-7.631],"t":68,"i":{"x":[1],"y":[1]},"o":{"x":[0],"y":[0]}},{"s":[-7.787],"t":69,"i":{"x":[1],"y":[1]},"o":{"x":[0],"y":[0]}},{"s":[-7.91],"t":70,"i":{"x":[1],"y":[1]},"o":{"x":[0],"y":[0]}},{"s":[-8.002],"t":71,"i":{"x":[1],"y":[1]},"o":{"x":[0],"y":[0]}},{"s":[-8.061],"t":72,"i":{"x":[1],"y":[1]},"o":{"x":[0],"y":[0]}},{"s":[-8.088],"t":73,"i":{"x":[1],"y":[1]},"o":{"x":[0],"y":[0]}},{"s":[-8.083],"t":74,"i":{"x":[1],"y":[1]},"o":{"x":[0],"y":[0]}},{"s":[-8.047],"t":75,"i":{"x":[1],"y":[1]},"o":{"x":[0],"y":[0]}},{"s":[-7.979],"t":76,"i":{"x":[1],"y":[1]},"o":{"x":[0],"y":[0]}},{"s":[-7.881],"t":77,"i":{"x":[1],"y":[1]},"o":{"x":[0],"y":[0]}},{"s":[-7.751],"t":78,"i":{"x":[1],"y":[1]},"o":{"x":[0],"y":[0]}},{"s":[-7.591],"t":79,"i":{"x":[1],"y":[1]},"o":{"x":[0],"y":[0]}},{"s":[-7.401],"t":80,"i":{"x":[1],"y":[1]},"o":{"x":[0],"y":[0]}},{"s":[-7.18],"t":81,"i":{"x":[1],"y":[1]},"o":{"x":[0],"y":[0]}},{"s":[-6.929],"t":82,"i":{"x":[1],"y":[1]},"o":{"x":[0],"y":[0]}},{"s":[-6.649],"t":83,"i":{"x":[1],"y":[1]},"o":{"x":[0],"y":[0]}},{"s":[-6.341],"t":84,"i":{"x":[1],"y":[1]},"o":{"x":[0],"y":[0]}},{"s":[-6.003],"t":85,"i":{"x":[1],"y":[1]},"o":{"x":[0],"y":[0]}},{"s":[-5.639],"t":86,"i":{"x":[1],"y":[1]},"o":{"x":[0],"y":[0]}},{"s":[-5.247],"t":87,"i":{"x":[1],"y":[1]},"o":{"x":[0],"y":[0]}},{"s":[-4.829],"t":88,"i":{"x":[1],"y":[1]},"o":{"x":[0],"y":[0]}},{"s":[-4.386],"t":89,"i":{"x":[1],"y":[1]},"o":{"x":[0],"y":[0]}},{"s":[-3.919],"t":90,"i":{"x":[1],"y":[1]},"o":{"x":[0],"y":[0]}},{"s":[-3.43],"t":91,"i":{"x":[1],"y":[1]},"o":{"x":[0],"y":[0]}},{"s":[-2.919],"t":92,"i":{"x":[1],"y":[1]},"o":{"x":[0],"y":[0]}},{"s":[-2.389],"t":93,"i":{"x":[1],"y":[1]},"o":{"x":[0],"y":[0]}},{"s":[-1.84],"t":94,"i":{"x":[1],"y":[1]},"o":{"x":[0],"y":[0]}},{"s":[-1.276],"t":95,"i":{"x":[1],"y":[1]},"o":{"x":[0],"y":[0]}},{"s":[-0.697],"t":96,"i":{"x":[1],"y":[1]},"o":{"x":[0],"y":[0]}},{"s":[-0.107],"t":97,"i":{"x":[1],"y":[1]},"o":{"x":[0],"y":[0]}},{"s":[0.492],"t":98,"i":{"x":[1],"y":[1]},"o":{"x":[0],"y":[0]}},{"s":[1.097],"t":99,"i":{"x":[1],"y":[1]},"o":{"x":[0],"y":[0]}},{"s":[2.315],"t":101,"i":{"x":[1],"y":[1]},"o":{"x":[0],"y":[0]}}]},"p":{"k":[{"s":[509.925,539.585,0],"t":0,"i":{"x":1,"y":1},"o":{"x":0,"y":0}},{"s":[510.732,539.322,0],"t":1,"i":{"x":1,"y":1},"o":{"x":0,"y":0}},{"s":[511.494,539.144,0],"t":2,"i":{"x":1,"y":1},"o":{"x":0,"y":0}},{"s":[512.203,539.054,0],"t":3,"i":{"x":1,"y":1},"o":{"x":0,"y":0}},{"s":[512.856,539.053,0],"t":4,"i":{"x":1,"y":1},"o":{"x":0,"y":0}},{"s":[513.446,539.144,0],"t":5,"i":{"x":1,"y":1},"o":{"x":0,"y":0}},{"s":[513.968,539.329,0],"t":6,"i":{"x":1,"y":1},"o":{"x":0,"y":0}},{"s":[514.425,539.599,0],"t":7,"i":{"x":1,"y":1},"o":{"x":0,"y":0}},{"s":[514.854,539.911,0],"t":8,"i":{"x":1,"y":1},"o":{"x":0,"y":0}},{"s":[515.255,540.259,0],"t":9,"i":{"x":1,"y":1},"o":{"x":0,"y":0}},{"s":[515.627,540.642,0],"t":10,"i":{"x":1,"y":1},"o":{"x":0,"y":0}},{"s":[515.968,541.058,0],"t":11,"i":{"x":1,"y":1},"o":{"x":0,"y":0}},{"s":[516.274,541.505,0],"t":12,"i":{"x":1,"y":1},"o":{"x":0,"y":0}},{"s":[516.543,541.982,0],"t":13,"i":{"x":1,"y":1},"o":{"x":0,"y":0}},{"s":[516.775,542.486,0],"t":14,"i":{"x":1,"y":1},"o":{"x":0,"y":0}},{"s":[516.968,543.017,0],"t":15,"i":{"x":1,"y":1},"o":{"x":0,"y":0}},{"s":[517.12,543.573,0],"t":16,"i":{"x":1,"y":1},"o":{"x":0,"y":0}},{"s":[517.231,544.152,0],"t":17,"i":{"x":1,"y":1},"o":{"x":0,"y":0}},{"s":[517.3,544.752,0],"t":18,"i":{"x":1,"y":1},"o":{"x":0,"y":0}},{"s":[517.327,545.372,0],"t":19,"i":{"x":1,"y":1},"o":{"x":0,"y":0}},{"s":[517.31,546.01,0],"t":20,"i":{"x":1,"y":1},"o":{"x":0,"y":0}},{"s":[517.251,546.664,0],"t":21,"i":{"x":1,"y":1},"o":{"x":0,"y":0}},{"s":[517.149,547.334,0],"t":22,"i":{"x":1,"y":1},"o":{"x":0,"y":0}},{"s":[517.003,548.017,0],"t":23,"i":{"x":1,"y":1},"o":{"x":0,"y":0}},{"s":[516.816,548.711,0],"t":24,"i":{"x":1,"y":1},"o":{"x":0,"y":0}},{"s":[516.586,549.416,0],"t":25,"i":{"x":1,"y":1},"o":{"x":0,"y":0}},{"s":[516.314,550.13,0],"t":26,"i":{"x":1,"y":1},"o":{"x":0,"y":0}},{"s":[516.001,550.852,0],"t":27,"i":{"x":1,"y":1},"o":{"x":0,"y":0}},{"s":[515.647,551.58,0],"t":28,"i":{"x":1,"y":1},"o":{"x":0,"y":0}},{"s":[515.253,552.314,0],"t":29,"i":{"x":1,"y":1},"o":{"x":0,"y":0}},{"s":[514.82,553.051,0],"t":30,"i":{"x":1,"y":1},"o":{"x":0,"y":0}},{"s":[514.349,553.793,0],"t":31,"i":{"x":1,"y":1},"o":{"x":0,"y":0}},{"s":[513.839,554.536,0],"t":32,"i":{"x":1,"y":1},"o":{"x":0,"y":0}},{"s":[513.293,555.281,0],"t":33,"i":{"x":1,"y":1},"o":{"x":0,"y":0}},{"s":[512.71,556.027,0],"t":34,"i":{"x":1,"y":1},"o":{"x":0,"y":0}},{"s":[512.09,556.773,0],"t":35,"i":{"x":1,"y":1},"o":{"x":0,"y":0}},{"s":[511.436,557.52,0],"t":36,"i":{"x":1,"y":1},"o":{"x":0,"y":0}},{"s":[510.747,558.266,0],"t":37,"i":{"x":1,"y":1},"o":{"x":0,"y":0}},{"s":[510.023,559.012,0],"t":38,"i":{"x":1,"y":1},"o":{"x":0,"y":0}},{"s":[509.265,559.757,0],"t":39,"i":{"x":1,"y":1},"o":{"x":0,"y":0}},{"s":[508.473,560.503,0],"t":40,"i":{"x":1,"y":1},"o":{"x":0,"y":0}},{"s":[507.647,561.248,0],"t":41,"i":{"x":1,"y":1},"o":{"x":0,"y":0}},{"s":[506.788,561.995,0],"t":42,"i":{"x":1,"y":1},"o":{"x":0,"y":0}},{"s":[505.893,562.742,0],"t":43,"i":{"x":1,"y":1},"o":{"x":0,"y":0}},{"s":[504.964,563.493,0],"t":44,"i":{"x":1,"y":1},"o":{"x":0,"y":0}},{"s":[504,564.246,0],"t":45,"i":{"x":1,"y":1},"o":{"x":0,"y":0}},{"s":[502.999,565.005,0],"t":46,"i":{"x":1,"y":1},"o":{"x":0,"y":0}},{"s":[501.961,565.77,0],"t":47,"i":{"x":1,"y":1},"o":{"x":0,"y":0}},{"s":[500.884,566.542,0],"t":48,"i":{"x":1,"y":1},"o":{"x":0,"y":0}},{"s":[499.772,567.316,0],"t":49,"i":{"x":1,"y":1},"o":{"x":0,"y":0}},{"s":[498.646,568.054,0],"t":50,"i":{"x":1,"y":1},"o":{"x":0,"y":0}},{"s":[497.516,568.747,0],"t":51,"i":{"x":1,"y":1},"o":{"x":0,"y":0}},{"s":[496.387,569.394,0],"t":52,"i":{"x":1,"y":1},"o":{"x":0,"y":0}},{"s":[495.268,569.991,0],"t":53,"i":{"x":1,"y":1},"o":{"x":0,"y":0}},{"s":[494.163,570.537,0],"t":54,"i":{"x":1,"y":1},"o":{"x":0,"y":0}},{"s":[493.081,571.028,0],"t":55,"i":{"x":1,"y":1},"o":{"x":0,"y":0}},{"s":[492.026,571.463,0],"t":56,"i":{"x":1,"y":1},"o":{"x":0,"y":0}},{"s":[491.007,571.839,0],"t":57,"i":{"x":1,"y":1},"o":{"x":0,"y":0}},{"s":[490.028,572.155,0],"t":58,"i":{"x":1,"y":1},"o":{"x":0,"y":0}},{"s":[489.097,572.408,0],"t":59,"i":{"x":1,"y":1},"o":{"x":0,"y":0}},{"s":[488.219,572.598,0],"t":60,"i":{"x":1,"y":1},"o":{"x":0,"y":0}},{"s":[487.4,572.722,0],"t":61,"i":{"x":1,"y":1},"o":{"x":0,"y":0}},{"s":[486.646,572.78,0],"t":62,"i":{"x":1,"y":1},"o":{"x":0,"y":0}},{"s":[485.962,572.77,0],"t":63,"i":{"x":1,"y":1},"o":{"x":0,"y":0}},{"s":[485.352,572.692,0],"t":64,"i":{"x":1,"y":1},"o":{"x":0,"y":0}},{"s":[484.822,572.544,0],"t":65,"i":{"x":1,"y":1},"o":{"x":0,"y":0}},{"s":[484.376,572.328,0],"t":66,"i":{"x":1,"y":1},"o":{"x":0,"y":0}},{"s":[484.016,572.047,0],"t":67,"i":{"x":1,"y":1},"o":{"x":0,"y":0}},{"s":[483.744,571.724,0],"t":68,"i":{"x":1,"y":1},"o":{"x":0,"y":0}},{"s":[483.555,571.36,0],"t":69,"i":{"x":1,"y":1},"o":{"x":0,"y":0}},{"s":[483.447,570.953,0],"t":70,"i":{"x":1,"y":1},"o":{"x":0,"y":0}},{"s":[483.418,570.502,0],"t":71,"i":{"x":1,"y":1},"o":{"x":0,"y":0}},{"s":[483.465,570.006,0],"t":72,"i":{"x":1,"y":1},"o":{"x":0,"y":0}},{"s":[483.585,569.463,0],"t":73,"i":{"x":1,"y":1},"o":{"x":0,"y":0}},{"s":[483.777,568.874,0],"t":74,"i":{"x":1,"y":1},"o":{"x":0,"y":0}},{"s":[484.038,568.238,0],"t":75,"i":{"x":1,"y":1},"o":{"x":0,"y":0}},{"s":[484.368,567.554,0],"t":76,"i":{"x":1,"y":1},"o":{"x":0,"y":0}},{"s":[484.763,566.824,0],"t":77,"i":{"x":1,"y":1},"o":{"x":0,"y":0}},{"s":[485.223,566.047,0],"t":78,"i":{"x":1,"y":1},"o":{"x":0,"y":0}},{"s":[485.745,565.225,0],"t":79,"i":{"x":1,"y":1},"o":{"x":0,"y":0}},{"s":[486.328,564.358,0],"t":80,"i":{"x":1,"y":1},"o":{"x":0,"y":0}},{"s":[486.971,563.448,0],"t":81,"i":{"x":1,"y":1},"o":{"x":0,"y":0}},{"s":[487.671,562.496,0],"t":82,"i":{"x":1,"y":1},"o":{"x":0,"y":0}},{"s":[488.426,561.505,0],"t":83,"i":{"x":1,"y":1},"o":{"x":0,"y":0}},{"s":[489.236,560.475,0],"t":84,"i":{"x":1,"y":1},"o":{"x":0,"y":0}},{"s":[490.097,559.411,0],"t":85,"i":{"x":1,"y":1},"o":{"x":0,"y":0}},{"s":[491.008,558.314,0],"t":86,"i":{"x":1,"y":1},"o":{"x":0,"y":0}},{"s":[491.967,557.187,0],"t":87,"i":{"x":1,"y":1},"o":{"x":0,"y":0}},{"s":[492.972,556.034,0],"t":88,"i":{"x":1,"y":1},"o":{"x":0,"y":0}},{"s":[494.019,554.858,0],"t":89,"i":{"x":1,"y":1},"o":{"x":0,"y":0}},{"s":[495.106,553.663,0],"t":90,"i":{"x":1,"y":1},"o":{"x":0,"y":0}},{"s":[496.23,552.453,0],"t":91,"i":{"x":1,"y":1},"o":{"x":0,"y":0}},{"s":[497.389,551.232,0],"t":92,"i":{"x":1,"y":1},"o":{"x":0,"y":0}},{"s":[498.577,550.005,0],"t":93,"i":{"x":1,"y":1},"o":{"x":0,"y":0}},{"s":[499.793,548.777,0],"t":94,"i":{"x":1,"y":1},"o":{"x":0,"y":0}},{"s":[501.032,547.553,0],"t":95,"i":{"x":1,"y":1},"o":{"x":0,"y":0}},{"s":[502.288,546.338,0],"t":96,"i":{"x":1,"y":1},"o":{"x":0,"y":0}},{"s":[503.559,545.138,0],"t":97,"i":{"x":1,"y":1},"o":{"x":0,"y":0}},{"s":[504.838,543.96,0],"t":98,"i":{"x":1,"y":1},"o":{"x":0,"y":0}},{"s":[506.12,542.808,0],"t":99,"i":{"x":1,"y":1},"o":{"x":0,"y":0}},{"s":[507.4,541.691,0],"t":100,"i":{"x":1,"y":1},"o":{"x":0,"y":0}},{"s":[508.671,540.614,0],"t":101,"i":{"x":1,"y":1},"o":{"x":0,"y":0}}]},"a":{"a":0,"k":[0,0,0]},"s":{"a":0,"k":[100,100,100]}},"ao":0,"shapes":[{"ty":"gr","it":[{"ind":0,"ty":"sh","ks":{"a":0,"k":{"i":[[36.21,-113.47],[113.46,36.211],[24.3,53.721],[0,0],[0,0],[-5.61,17.58],[-113.46,-36.2]],"o":[[-36.2,113.47],[-60.59,-19.34],[0,0],[0,0],[1.04,-17.609],[36.2,-113.46],[113.47,36.21]],"v":[[244.937,65.558],[-26.063,205.447],[-157.053,88.777],[-255.203,41.118],[-175.843,-12.603],[-165.953,-65.563],[105.047,-205.452]],"c":true}},"nm":"Path 1","hd":false},{"ty":"st","c":{"a":0,"k":[0.007843137719,0.007843137719,0.007843137719,1]},"o":{"a":0,"k":100},"w":{"a":0,"k":1.7},"lc":2,"lj":2,"bm":0,"nm":"Stroke 1","hd":false},{"ty":"fl","c":{"a":0,"k":[1,1,1,1]},"o":{"a":0,"k":100},"r":1,"bm":0,"nm":"Fill 1","hd":false},{"ty":"tr","p":{"a":0,"k":[0,0]},"a":{"a":0,"k":[0,0]},"s":{"a":0,"k":[100,100]},"r":{"a":0,"k":0},"o":{"a":0,"k":100},"sk":{"a":0,"k":0},"sa":{"a":0,"k":0},"nm":"Transform"}],"nm":"Group 1","bm":0,"hd":false}],"ip":0,"op":151,"st":0,"ct":1,"bm":0},{"ddd":0,"ind":3,"ty":4,"nm":"M 1","td":1,"sr":1,"ks":{"o":{"a":0,"k":100},"r":{"a":0,"k":0},"p":{"k":[{"s":[883.376,941.837,0],"t":1,"i":{"x":1,"y":1},"o":{"x":0,"y":0}},{"s":[882.91,942.808,0],"t":2,"i":{"x":1,"y":1},"o":{"x":0,"y":0}},{"s":[882.394,943.835,0],"t":3,"i":{"x":1,"y":1},"o":{"x":0,"y":0}},{"s":[881.83,944.916,0],"t":4,"i":{"x":1,"y":1},"o":{"x":0,"y":0}},{"s":[881.22,946.047,0],"t":5,"i":{"x":1,"y":1},"o":{"x":0,"y":0}},{"s":[880.565,947.227,0],"t":6,"i":{"x":1,"y":1},"o":{"x":0,"y":0}},{"s":[879.866,948.453,0],"t":7,"i":{"x":1,"y":1},"o":{"x":0,"y":0}},{"s":[879.127,949.722,0],"t":8,"i":{"x":1,"y":1},"o":{"x":0,"y":0}},{"s":[878.348,951.031,0],"t":9,"i":{"x":1,"y":1},"o":{"x":0,"y":0}},{"s":[877.531,952.375,0],"t":10,"i":{"x":1,"y":1},"o":{"x":0,"y":0}},{"s":[876.679,953.752,0],"t":11,"i":{"x":1,"y":1},"o":{"x":0,"y":0}},{"s":[875.792,955.157,0],"t":12,"i":{"x":1,"y":1},"o":{"x":0,"y":0}},{"s":[874.873,956.586,0],"t":13,"i":{"x":1,"y":1},"o":{"x":0,"y":0}},{"s":[873.922,958.034,0],"t":14,"i":{"x":1,"y":1},"o":{"x":0,"y":0}},{"s":[872.942,959.496,0],"t":15,"i":{"x":1,"y":1},"o":{"x":0,"y":0}},{"s":[871.932,960.968,0],"t":16,"i":{"x":1,"y":1},"o":{"x":0,"y":0}},{"s":[870.895,962.445,0],"t":17,"i":{"x":1,"y":1},"o":{"x":0,"y":0}},{"s":[869.831,963.92,0],"t":18,"i":{"x":1,"y":1},"o":{"x":0,"y":0}},{"s":[868.745,965.389,0],"t":19,"i":{"x":1,"y":1},"o":{"x":0,"y":0}},{"s":[867.641,966.845,0],"t":20,"i":{"x":1,"y":1},"o":{"x":0,"y":0}},{"s":[866.524,968.281,0],"t":21,"i":{"x":1,"y":1},"o":{"x":0,"y":0}},{"s":[865.4,969.692,0],"t":22,"i":{"x":1,"y":1},"o":{"x":0,"y":0}},{"s":[864.275,971.072,0],"t":23,"i":{"x":1,"y":1},"o":{"x":0,"y":0}},{"s":[863.153,972.414,0],"t":24,"i":{"x":1,"y":1},"o":{"x":0,"y":0}},{"s":[862.043,973.711,0],"t":25,"i":{"x":1,"y":1},"o":{"x":0,"y":0}},{"s":[860.949,974.958,0],"t":26,"i":{"x":1,"y":1},"o":{"x":0,"y":0}},{"s":[859.88,976.147,0],"t":27,"i":{"x":1,"y":1},"o":{"x":0,"y":0}},{"s":[858.84,977.273,0],"t":28,"i":{"x":1,"y":1},"o":{"x":0,"y":0}},{"s":[857.838,978.329,0],"t":29,"i":{"x":1,"y":1},"o":{"x":0,"y":0}},{"s":[856.881,979.31,0],"t":30,"i":{"x":1,"y":1},"o":{"x":0,"y":0}},{"s":[855.975,980.208,0],"t":31,"i":{"x":1,"y":1},"o":{"x":0,"y":0}},{"s":[855.128,981.017,0],"t":32,"i":{"x":1,"y":1},"o":{"x":0,"y":0}},{"s":[854.347,981.733,0],"t":33,"i":{"x":1,"y":1},"o":{"x":0,"y":0}},{"s":[853.639,982.35,0],"t":34,"i":{"x":1,"y":1},"o":{"x":0,"y":0}},{"s":[853.011,982.861,0],"t":35,"i":{"x":1,"y":1},"o":{"x":0,"y":0}},{"s":[852.471,983.265,0],"t":36,"i":{"x":1,"y":1},"o":{"x":0,"y":0}},{"s":[851.709,983.862,0],"t":38,"i":{"x":1,"y":1},"o":{"x":0,"y":0}},{"s":[852.475,983.154,0],"t":47,"i":{"x":1,"y":1},"o":{"x":0,"y":0}},{"s":[852.881,982.714,0],"t":48,"i":{"x":1,"y":1},"o":{"x":0,"y":0}},{"s":[853.337,982.202,0],"t":49,"i":{"x":1,"y":1},"o":{"x":0,"y":0}},{"s":[853.839,981.618,0],"t":50,"i":{"x":1,"y":1},"o":{"x":0,"y":0}},{"s":[854.383,980.963,0],"t":51,"i":{"x":1,"y":1},"o":{"x":0,"y":0}},{"s":[854.969,980.24,0],"t":52,"i":{"x":1,"y":1},"o":{"x":0,"y":0}},{"s":[855.592,979.45,0],"t":53,"i":{"x":1,"y":1},"o":{"x":0,"y":0}},{"s":[856.251,978.594,0],"t":54,"i":{"x":1,"y":1},"o":{"x":0,"y":0}},{"s":[856.943,977.675,0],"t":55,"i":{"x":1,"y":1},"o":{"x":0,"y":0}},{"s":[857.667,976.696,0],"t":56,"i":{"x":1,"y":1},"o":{"x":0,"y":0}},{"s":[858.419,975.661,0],"t":57,"i":{"x":1,"y":1},"o":{"x":0,"y":0}},{"s":[859.198,974.571,0],"t":58,"i":{"x":1,"y":1},"o":{"x":0,"y":0}},{"s":[860.002,973.432,0],"t":59,"i":{"x":1,"y":1},"o":{"x":0,"y":0}},{"s":[860.83,972.247,0],"t":60,"i":{"x":1,"y":1},"o":{"x":0,"y":0}},{"s":[861.678,971.02,0],"t":61,"i":{"x":1,"y":1},"o":{"x":0,"y":0}},{"s":[862.546,969.757,0],"t":62,"i":{"x":1,"y":1},"o":{"x":0,"y":0}},{"s":[863.431,968.463,0],"t":63,"i":{"x":1,"y":1},"o":{"x":0,"y":0}},{"s":[864.33,967.143,0],"t":64,"i":{"x":1,"y":1},"o":{"x":0,"y":0}},{"s":[865.243,965.804,0],"t":65,"i":{"x":1,"y":1},"o":{"x":0,"y":0}},{"s":[866.167,964.451,0],"t":66,"i":{"x":1,"y":1},"o":{"x":0,"y":0}},{"s":[867.098,963.093,0],"t":67,"i":{"x":1,"y":1},"o":{"x":0,"y":0}},{"s":[868.036,961.735,0],"t":68,"i":{"x":1,"y":1},"o":{"x":0,"y":0}},{"s":[868.976,960.386,0],"t":69,"i":{"x":1,"y":1},"o":{"x":0,"y":0}},{"s":[869.917,959.053,0],"t":70,"i":{"x":1,"y":1},"o":{"x":0,"y":0}},{"s":[870.855,957.745,0],"t":71,"i":{"x":1,"y":1},"o":{"x":0,"y":0}},{"s":[871.786,956.472,0],"t":72,"i":{"x":1,"y":1},"o":{"x":0,"y":0}},{"s":[872.707,955.242,0],"t":73,"i":{"x":1,"y":1},"o":{"x":0,"y":0}},{"s":[873.614,954.066,0],"t":74,"i":{"x":1,"y":1},"o":{"x":0,"y":0}},{"s":[874.503,952.953,0],"t":75,"i":{"x":1,"y":1},"o":{"x":0,"y":0}},{"s":[875.37,951.915,0],"t":76,"i":{"x":1,"y":1},"o":{"x":0,"y":0}},{"s":[876.208,950.962,0],"t":77,"i":{"x":1,"y":1},"o":{"x":0,"y":0}},{"s":[877.015,950.102,0],"t":78,"i":{"x":1,"y":1},"o":{"x":0,"y":0}},{"s":[877.8,949.272,0],"t":79,"i":{"x":1,"y":1},"o":{"x":0,"y":0}},{"s":[878.562,948.454,0],"t":80,"i":{"x":1,"y":1},"o":{"x":0,"y":0}},{"s":[879.299,947.653,0],"t":81,"i":{"x":1,"y":1},"o":{"x":0,"y":0}},{"s":[880.006,946.872,0],"t":82,"i":{"x":1,"y":1},"o":{"x":0,"y":0}},{"s":[880.68,946.117,0],"t":83,"i":{"x":1,"y":1},"o":{"x":0,"y":0}},{"s":[881.317,945.392,0],"t":84,"i":{"x":1,"y":1},"o":{"x":0,"y":0}},{"s":[881.913,944.701,0],"t":85,"i":{"x":1,"y":1},"o":{"x":0,"y":0}},{"s":[882.465,944.047,0],"t":86,"i":{"x":1,"y":1},"o":{"x":0,"y":0}},{"s":[882.971,943.435,0],"t":87,"i":{"x":1,"y":1},"o":{"x":0,"y":0}},{"s":[883.428,942.867,0],"t":88,"i":{"x":1,"y":1},"o":{"x":0,"y":0}},{"s":[883.833,942.348,0],"t":89,"i":{"x":1,"y":1},"o":{"x":0,"y":0}},{"s":[884.479,941.466,0],"t":91,"i":{"x":1,"y":1},"o":{"x":0,"y":0}},{"s":[885.015,940.57,0],"t":94,"i":{"x":1,"y":1},"o":{"x":0,"y":0}}]},"a":{"a":0,"k":[0,0,0]},"s":{"a":0,"k":[100,100,100]}},"ao":0,"shapes":[{"ty":"gr","it":[{"ind":0,"ty":"sh","ks":{"a":0,"k":{"i":[[0,-23.399],[0,0],[14.52,0],[0,0],[0,0],[0,0],[0,0],[0,23.4],[0,0],[-14.51,0],[0,0]],"o":[[0,0],[0,23.4],[0,0],[0,0],[0,0],[0,0],[-14.51,0],[0,0],[0,-23.399],[0,0],[14.52,0]],"v":[[317.59,-240.38],[317.59,109.32],[291.46,151.78],[219.92,151.78],[219.92,282.84],[117.89,151.78],[-291.26,151.78],[-317.59,109.32],[-317.59,-240.38],[-291.26,-282.84],[291.46,-282.84]],"c":true}},"nm":"Path 1","hd":false},{"ty":"fl","c":{"a":0,"k":[0.274509817362,0.509803950787,0.92549020052,1]},"o":{"a":0,"k":100},"r":1,"bm":0,"nm":"Fill 1","hd":false},{"ty":"tr","p":{"a":0,"k":[0,0]},"a":{"a":0,"k":[0,0]},"s":{"a":0,"k":[100,100]},"r":{"a":0,"k":0},"o":{"a":0,"k":100},"sk":{"a":0,"k":0},"sa":{"a":0,"k":0},"nm":"Transform"}],"nm":"Group 1","bm":0,"hd":false}],"ip":0,"op":151,"st":0,"ct":1,"bm":0},{"ddd":0,"ind":4,"ty":4,"nm":"shadow","parent":2,"tt":1,"sr":1,"ks":{"o":{"a":0,"k":100},"r":{"a":0,"k":0},"p":{"a":0,"k":[136.559,238.723,0]},"a":{"a":0,"k":[0,0,0]},"s":{"a":0,"k":[100,100,100]}},"ao":0,"shapes":[{"ty":"gr","it":[{"ind":0,"ty":"sh","ks":{"a":0,"k":{"i":[[0,0],[0,0],[0,0],[0,0],[-14.51,0]],"o":[[0,0],[0,0],[0,0],[0,-23.399],[0,0]],"v":[[82.085,-118.58],[-132.085,170.294],[-132.085,156.576],[-140.085,-76.406],[-113.755,-118.866]],"c":true}},"nm":"Path 1","hd":false},{"ty":"fl","c":{"a":0,"k":[0.007843137719,0.007843137719,0.007843137719,1]},"o":{"a":0,"k":100},"r":1,"bm":0,"nm":"Fill 1","hd":false},{"ty":"tr","p":{"a":0,"k":[0,0]},"a":{"a":0,"k":[0,0]},"s":{"a":0,"k":[100,100]},"r":{"a":0,"k":0},"o":{"a":0,"k":100},"sk":{"a":0,"k":0},"sa":{"a":0,"k":0},"nm":"Transform"}],"nm":"Group 1","bm":0,"hd":false}],"ip":0,"op":151,"st":0,"ct":1,"bm":0},{"ddd":0,"ind":5,"ty":4,"nm":"L 4","parent":3,"sr":1,"ks":{"o":{"a":0,"k":100},"r":{"a":0,"k":0},"p":{"a":0,"k":[-0.001,46.922,0]},"a":{"a":0,"k":[0,0,0]},"s":{"a":0,"k":[100,100,100]}},"ao":0,"shapes":[{"ty":"gr","it":[{"ind":0,"ty":"sh","ks":{"a":1,"k":[{"i":{"x":0.25,"y":1},"o":{"x":0.33,"y":0},"t":6,"s":[{"i":[[8.976,0],[0,0],[0,8.976],[-8.976,0],[0,0],[0,-8.976]],"o":[[0,0],[-8.976,0],[0,-8.976],[0,0],[8.976,0],[0,8.976]],"v":[[240.045,16.253],[-240.045,16.253],[-256.298,0],[-240.045,-16.253],[240.045,-16.253],[256.298,0]],"c":true}]},{"i":{"x":0.25,"y":1},"o":{"x":0.33,"y":0},"t":14,"s":[{"i":[[8.976,0],[0,0],[0,8.976],[-8.976,0],[0,0],[0,-8.976]],"o":[[0,0],[-8.976,0],[0,-8.976],[0,0],[8.976,0],[0,8.976]],"v":[[40.045,16.253],[-240.045,16.253],[-256.298,0],[-240.045,-16.253],[40.045,-16.253],[56.298,0]],"c":true}]},{"i":{"x":0.833,"y":1},"o":{"x":0.167,"y":0},"t":24,"s":[{"i":[[8.976,0],[0,0],[0,8.976],[-8.976,0],[0,0],[0,-8.976]],"o":[[0,0],[-8.976,0],[0,-8.976],[0,0],[8.976,0],[0,8.976]],"v":[[240.045,16.253],[-240.045,16.253],[-256.298,0],[-240.045,-16.253],[240.045,-16.253],[256.298,0]],"c":true}]},{"i":{"x":0.25,"y":1},"o":{"x":0.33,"y":0},"t":40,"s":[{"i":[[8.976,0],[0,0],[0,8.976],[-8.976,0],[0,0],[0,-8.976]],"o":[[0,0],[-8.976,0],[0,-8.976],[0,0],[8.976,0],[0,8.976]],"v":[[240.045,16.253],[-240.045,16.253],[-256.298,0],[-240.045,-16.253],[240.045,-16.253],[256.298,0]],"c":true}]},{"i":{"x":0.25,"y":1},"o":{"x":0.33,"y":0},"t":48,"s":[{"i":[[8.976,0],[0,0],[0,8.976],[-8.976,0],[0,0],[0,-8.976]],"o":[[0,0],[-8.976,0],[0,-8.976],[0,0],[8.976,0],[0,8.976]],"v":[[40.045,16.253],[-240.045,16.253],[-256.298,0],[-240.045,-16.253],[40.045,-16.253],[56.298,0]],"c":true}]},{"i":{"x":0.833,"y":1},"o":{"x":0.167,"y":0},"t":58,"s":[{"i":[[8.976,0],[0,0],[0,8.976],[-8.976,0],[0,0],[0,-8.976]],"o":[[0,0],[-8.976,0],[0,-8.976],[0,0],[8.976,0],[0,8.976]],"v":[[240.045,16.253],[-240.045,16.253],[-256.298,0],[-240.045,-16.253],[240.045,-16.253],[256.298,0]],"c":true}]},{"i":{"x":0.25,"y":1},"o":{"x":0.33,"y":0},"t":74,"s":[{"i":[[8.976,0],[0,0],[0,8.976],[-8.976,0],[0,0],[0,-8.976]],"o":[[0,0],[-8.976,0],[0,-8.976],[0,0],[8.976,0],[0,8.976]],"v":[[240.045,16.253],[-240.045,16.253],[-256.298,0],[-240.045,-16.253],[240.045,-16.253],[256.298,0]],"c":true}]},{"i":{"x":0.25,"y":1},"o":{"x":0.33,"y":0},"t":82,"s":[{"i":[[8.976,0],[0,0],[0,8.976],[-8.976,0],[0,0],[0,-8.976]],"o":[[0,0],[-8.976,0],[0,-8.976],[0,0],[8.976,0],[0,8.976]],"v":[[40.045,16.253],[-240.045,16.253],[-256.298,0],[-240.045,-16.253],[40.045,-16.253],[56.298,0]],"c":true}]},{"t":92,"s":[{"i":[[8.976,0],[0,0],[0,8.976],[-8.976,0],[0,0],[0,-8.976]],"o":[[0,0],[-8.976,0],[0,-8.976],[0,0],[8.976,0],[0,8.976]],"v":[[240.045,16.253],[-240.045,16.253],[-256.298,0],[-240.045,-16.253],[240.045,-16.253],[256.298,0]],"c":true}]}]},"nm":"Path 1","hd":false},{"ty":"fl","c":{"a":0,"k":[1,1,1,1]},"o":{"a":0,"k":100},"r":1,"bm":0,"nm":"Fill 1","hd":false},{"ty":"tr","p":{"a":0,"k":[0,0]},"a":{"a":0,"k":[0,0]},"s":{"a":0,"k":[100,100]},"r":{"a":0,"k":0},"o":{"a":0,"k":100},"sk":{"a":0,"k":0},"sa":{"a":0,"k":0},"nm":"Transform"}],"nm":"Group 1","bm":0,"hd":false}],"ip":0,"op":151,"st":0,"ct":1,"bm":0},{"ddd":0,"ind":6,"ty":4,"nm":"L 6","parent":3,"sr":1,"ks":{"o":{"a":0,"k":100},"r":{"a":0,"k":0},"p":{"a":0,"k":[177.999,-62.794,0]},"a":{"a":0,"k":[0,0,0]},"s":{"a":0,"k":[100,100,100]}},"ao":0,"shapes":[{"ty":"gr","it":[{"ind":0,"ty":"sh","ks":{"a":1,"k":[{"i":{"x":0.25,"y":1},"o":{"x":0.33,"y":0},"t":4,"s":[{"i":[[8.976,0],[0,0],[0,8.976],[-8.976,0],[0,0],[0,-8.976]],"o":[[0,0],[-8.976,0],[0,-8.976],[0,0],[8.976,0],[0,8.976]],"v":[[-45.955,16.638],[-240.045,16.253],[-256.298,0],[-240.045,-16.253],[-45.955,-15.868],[-29.702,0.385]],"c":true}]},{"i":{"x":0.25,"y":1},"o":{"x":0.33,"y":0},"t":12,"s":[{"i":[[8.976,0],[0,0],[0,8.976],[-8.976,0],[0,0],[0,-8.976]],"o":[[0,0],[-8.976,0],[0,-8.976],[0,0],[8.976,0],[0,8.976]],"v":[[-176.955,16.951],[-240.045,16.253],[-256.298,0],[-240.045,-16.253],[-176.955,-15.555],[-160.702,0.698]],"c":true}]},{"i":{"x":0.25,"y":1},"o":{"x":0.33,"y":0},"t":22,"s":[{"i":[[8.976,0],[0,0],[0,8.976],[-8.976,0],[0,0],[0,-8.976]],"o":[[0,0],[-8.976,0],[0,-8.976],[0,0],[8.976,0],[0,8.976]],"v":[[-45.955,16.638],[-240.045,16.253],[-256.298,0],[-240.045,-16.253],[-45.955,-15.868],[-29.702,0.385]],"c":true}]},{"i":{"x":0.25,"y":1},"o":{"x":0.33,"y":0},"t":38,"s":[{"i":[[8.976,0],[0,0],[0,8.976],[-8.976,0],[0,0],[0,-8.976]],"o":[[0,0],[-8.976,0],[0,-8.976],[0,0],[8.976,0],[0,8.976]],"v":[[-45.955,16.638],[-240.045,16.253],[-256.298,0],[-240.045,-16.253],[-45.955,-15.868],[-29.702,0.385]],"c":true}]},{"i":{"x":0.25,"y":1},"o":{"x":0.33,"y":0},"t":46,"s":[{"i":[[8.976,0],[0,0],[0,8.976],[-8.976,0],[0,0],[0,-8.976]],"o":[[0,0],[-8.976,0],[0,-8.976],[0,0],[8.976,0],[0,8.976]],"v":[[-176.955,16.951],[-240.045,16.253],[-256.298,0],[-240.045,-16.253],[-176.955,-15.555],[-160.702,0.698]],"c":true}]},{"i":{"x":0.25,"y":1},"o":{"x":0.33,"y":0},"t":56,"s":[{"i":[[8.976,0],[0,0],[0,8.976],[-8.976,0],[0,0],[0,-8.976]],"o":[[0,0],[-8.976,0],[0,-8.976],[0,0],[8.976,0],[0,8.976]],"v":[[-45.955,16.638],[-240.045,16.253],[-256.298,0],[-240.045,-16.253],[-45.955,-15.868],[-29.702,0.385]],"c":true}]},{"i":{"x":0.25,"y":1},"o":{"x":0.33,"y":0},"t":72,"s":[{"i":[[8.976,0],[0,0],[0,8.976],[-8.976,0],[0,0],[0,-8.976]],"o":[[0,0],[-8.976,0],[0,-8.976],[0,0],[8.976,0],[0,8.976]],"v":[[-45.955,16.638],[-240.045,16.253],[-256.298,0],[-240.045,-16.253],[-45.955,-15.868],[-29.702,0.385]],"c":true}]},{"i":{"x":0.25,"y":1},"o":{"x":0.33,"y":0},"t":80,"s":[{"i":[[8.976,0],[0,0],[0,8.976],[-8.976,0],[0,0],[0,-8.976]],"o":[[0,0],[-8.976,0],[0,-8.976],[0,0],[8.976,0],[0,8.976]],"v":[[-176.955,16.951],[-240.045,16.253],[-256.298,0],[-240.045,-16.253],[-176.955,-15.555],[-160.702,0.698]],"c":true}]},{"t":90,"s":[{"i":[[8.976,0],[0,0],[0,8.976],[-8.976,0],[0,0],[0,-8.976]],"o":[[0,0],[-8.976,0],[0,-8.976],[0,0],[8.976,0],[0,8.976]],"v":[[-45.955,16.638],[-240.045,16.253],[-256.298,0],[-240.045,-16.253],[-45.955,-15.868],[-29.702,0.385]],"c":true}]}]},"nm":"Path 1","hd":false},{"ty":"fl","c":{"a":0,"k":[1,1,1,1]},"o":{"a":0,"k":100},"r":1,"bm":0,"nm":"Fill 1","hd":false},{"ty":"tr","p":{"a":0,"k":[0,0]},"a":{"a":0,"k":[0,0]},"s":{"a":0,"k":[100,100]},"r":{"a":0,"k":0},"o":{"a":0,"k":100},"sk":{"a":0,"k":0},"sa":{"a":0,"k":0},"nm":"Transform"}],"nm":"Group 1","bm":0,"hd":false}],"ip":0,"op":151,"st":0,"ct":1,"bm":0},{"ddd":0,"ind":7,"ty":4,"nm":"L 5","parent":3,"sr":1,"ks":{"o":{"a":0,"k":100},"r":{"a":0,"k":0},"p":{"a":0,"k":[-0.001,-62.794,0]},"a":{"a":0,"k":[0,0,0]},"s":{"a":0,"k":[100,100,100]}},"ao":0,"shapes":[{"ty":"gr","it":[{"ind":0,"ty":"sh","ks":{"a":1,"k":[{"i":{"x":0.25,"y":1},"o":{"x":0.33,"y":0},"t":2,"s":[{"i":[[8.976,0],[0,0],[0,8.976],[-8.976,0],[0,0],[0,-8.976]],"o":[[0,0],[-8.976,0],[0,-8.976],[0,0],[8.976,0],[0,8.976]],"v":[[-138.955,16.381],[-240.045,16.253],[-256.298,0],[-240.045,-16.253],[-138.955,-16.125],[-122.702,0.128]],"c":true}]},{"i":{"x":0.25,"y":1},"o":{"x":0.33,"y":0},"t":10,"s":[{"i":[[8.976,0],[0,0],[0,8.976],[-8.976,0],[0,0],[0,-8.976]],"o":[[0,0],[-8.976,0],[0,-8.976],[0,0],[8.976,0],[0,8.976]],"v":[[-202.955,16.438],[-240.045,16.253],[-256.298,0],[-240.045,-16.253],[-202.955,-16.068],[-186.702,0.185]],"c":true}]},{"i":{"x":0.25,"y":1},"o":{"x":0.33,"y":0},"t":20,"s":[{"i":[[8.976,0],[0,0],[0,8.976],[-8.976,0],[0,0],[0,-8.976]],"o":[[0,0],[-8.976,0],[0,-8.976],[0,0],[8.976,0],[0,8.976]],"v":[[-138.955,16.381],[-240.045,16.253],[-256.298,0],[-240.045,-16.253],[-138.955,-16.125],[-122.702,0.128]],"c":true}]},{"i":{"x":0.25,"y":1},"o":{"x":0.33,"y":0},"t":36,"s":[{"i":[[8.976,0],[0,0],[0,8.976],[-8.976,0],[0,0],[0,-8.976]],"o":[[0,0],[-8.976,0],[0,-8.976],[0,0],[8.976,0],[0,8.976]],"v":[[-138.955,16.381],[-240.045,16.253],[-256.298,0],[-240.045,-16.253],[-138.955,-16.125],[-122.702,0.128]],"c":true}]},{"i":{"x":0.25,"y":1},"o":{"x":0.33,"y":0},"t":44,"s":[{"i":[[8.976,0],[0,0],[0,8.976],[-8.976,0],[0,0],[0,-8.976]],"o":[[0,0],[-8.976,0],[0,-8.976],[0,0],[8.976,0],[0,8.976]],"v":[[-202.955,16.438],[-240.045,16.253],[-256.298,0],[-240.045,-16.253],[-202.955,-16.068],[-186.702,0.185]],"c":true}]},{"i":{"x":0.25,"y":1},"o":{"x":0.33,"y":0},"t":54,"s":[{"i":[[8.976,0],[0,0],[0,8.976],[-8.976,0],[0,0],[0,-8.976]],"o":[[0,0],[-8.976,0],[0,-8.976],[0,0],[8.976,0],[0,8.976]],"v":[[-138.955,16.381],[-240.045,16.253],[-256.298,0],[-240.045,-16.253],[-138.955,-16.125],[-122.702,0.128]],"c":true}]},{"i":{"x":0.25,"y":1},"o":{"x":0.33,"y":0},"t":70,"s":[{"i":[[8.976,0],[0,0],[0,8.976],[-8.976,0],[0,0],[0,-8.976]],"o":[[0,0],[-8.976,0],[0,-8.976],[0,0],[8.976,0],[0,8.976]],"v":[[-138.955,16.381],[-240.045,16.253],[-256.298,0],[-240.045,-16.253],[-138.955,-16.125],[-122.702,0.128]],"c":true}]},{"i":{"x":0.25,"y":1},"o":{"x":0.33,"y":0},"t":78,"s":[{"i":[[8.976,0],[0,0],[0,8.976],[-8.976,0],[0,0],[0,-8.976]],"o":[[0,0],[-8.976,0],[0,-8.976],[0,0],[8.976,0],[0,8.976]],"v":[[-202.955,16.438],[-240.045,16.253],[-256.298,0],[-240.045,-16.253],[-202.955,-16.068],[-186.702,0.185]],"c":true}]},{"t":88,"s":[{"i":[[8.976,0],[0,0],[0,8.976],[-8.976,0],[0,0],[0,-8.976]],"o":[[0,0],[-8.976,0],[0,-8.976],[0,0],[8.976,0],[0,8.976]],"v":[[-138.955,16.381],[-240.045,16.253],[-256.298,0],[-240.045,-16.253],[-138.955,-16.125],[-122.702,0.128]],"c":true}]}]},"nm":"Path 1","hd":false},{"ty":"fl","c":{"a":0,"k":[1,1,1,1]},"o":{"a":0,"k":100},"r":1,"bm":0,"nm":"Fill 1","hd":false},{"ty":"tr","p":{"a":0,"k":[0,0]},"a":{"a":0,"k":[0,0]},"s":{"a":0,"k":[100,100]},"r":{"a":0,"k":0},"o":{"a":0,"k":100},"sk":{"a":0,"k":0},"sa":{"a":0,"k":0},"nm":"Transform"}],"nm":"Group 1","bm":0,"hd":false}],"ip":0,"op":151,"st":0,"ct":1,"bm":0},{"ddd":0,"ind":8,"ty":4,"nm":"L 1","parent":3,"sr":1,"ks":{"o":{"a":0,"k":100},"r":{"a":0,"k":0},"p":{"a":0,"k":[-0.001,-170.794,0]},"a":{"a":0,"k":[0,0,0]},"s":{"a":0,"k":[100,100,100]}},"ao":0,"shapes":[{"ty":"gr","it":[{"ind":0,"ty":"sh","ks":{"a":1,"k":[{"i":{"x":0.25,"y":1},"o":{"x":0.33,"y":0},"t":0,"s":[{"i":[[8.976,0],[0,0],[0,8.976],[-8.976,0],[0,0],[0,-8.976]],"o":[[0,0],[-8.976,0],[0,-8.976],[0,0],[8.976,0],[0,8.976]],"v":[[240.045,16.253],[-240.045,16.253],[-256.298,0],[-240.045,-16.253],[240.045,-16.253],[256.298,0]],"c":true}]},{"i":{"x":0.25,"y":1},"o":{"x":0.33,"y":0},"t":8,"s":[{"i":[[8.976,0],[0,0],[0,8.976],[-8.976,0],[0,0],[0,-8.976]],"o":[[0,0],[-8.976,0],[0,-8.976],[0,0],[8.976,0],[0,8.976]],"v":[[40.045,16.253],[-240.045,16.253],[-256.298,0],[-240.045,-16.253],[40.045,-16.253],[56.298,0]],"c":true}]},{"i":{"x":0.25,"y":1},"o":{"x":0.167,"y":0},"t":18,"s":[{"i":[[8.976,0],[0,0],[0,8.976],[-8.976,0],[0,0],[0,-8.976]],"o":[[0,0],[-8.976,0],[0,-8.976],[0,0],[8.976,0],[0,8.976]],"v":[[240.045,16.253],[-240.045,16.253],[-256.298,0],[-240.045,-16.253],[240.045,-16.253],[256.298,0]],"c":true}]},{"i":{"x":0.25,"y":1},"o":{"x":0.33,"y":0},"t":34,"s":[{"i":[[8.976,0],[0,0],[0,8.976],[-8.976,0],[0,0],[0,-8.976]],"o":[[0,0],[-8.976,0],[0,-8.976],[0,0],[8.976,0],[0,8.976]],"v":[[240.045,16.253],[-240.045,16.253],[-256.298,0],[-240.045,-16.253],[240.045,-16.253],[256.298,0]],"c":true}]},{"i":{"x":0.25,"y":1},"o":{"x":0.33,"y":0},"t":42,"s":[{"i":[[8.976,0],[0,0],[0,8.976],[-8.976,0],[0,0],[0,-8.976]],"o":[[0,0],[-8.976,0],[0,-8.976],[0,0],[8.976,0],[0,8.976]],"v":[[40.045,16.253],[-240.045,16.253],[-256.298,0],[-240.045,-16.253],[40.045,-16.253],[56.298,0]],"c":true}]},{"i":{"x":0.25,"y":1},"o":{"x":0.167,"y":0},"t":52,"s":[{"i":[[8.976,0],[0,0],[0,8.976],[-8.976,0],[0,0],[0,-8.976]],"o":[[0,0],[-8.976,0],[0,-8.976],[0,0],[8.976,0],[0,8.976]],"v":[[240.045,16.253],[-240.045,16.253],[-256.298,0],[-240.045,-16.253],[240.045,-16.253],[256.298,0]],"c":true}]},{"i":{"x":0.25,"y":1},"o":{"x":0.33,"y":0},"t":68,"s":[{"i":[[8.976,0],[0,0],[0,8.976],[-8.976,0],[0,0],[0,-8.976]],"o":[[0,0],[-8.976,0],[0,-8.976],[0,0],[8.976,0],[0,8.976]],"v":[[240.045,16.253],[-240.045,16.253],[-256.298,0],[-240.045,-16.253],[240.045,-16.253],[256.298,0]],"c":true}]},{"i":{"x":0.25,"y":1},"o":{"x":0.33,"y":0},"t":76,"s":[{"i":[[8.976,0],[0,0],[0,8.976],[-8.976,0],[0,0],[0,-8.976]],"o":[[0,0],[-8.976,0],[0,-8.976],[0,0],[8.976,0],[0,8.976]],"v":[[40.045,16.253],[-240.045,16.253],[-256.298,0],[-240.045,-16.253],[40.045,-16.253],[56.298,0]],"c":true}]},{"t":86,"s":[{"i":[[8.976,0],[0,0],[0,8.976],[-8.976,0],[0,0],[0,-8.976]],"o":[[0,0],[-8.976,0],[0,-8.976],[0,0],[8.976,0],[0,8.976]],"v":[[240.045,16.253],[-240.045,16.253],[-256.298,0],[-240.045,-16.253],[240.045,-16.253],[256.298,0]],"c":true}]}]},"nm":"Path 1","hd":false},{"ty":"fl","c":{"a":0,"k":[1,1,1,1]},"o":{"a":0,"k":100},"r":1,"bm":0,"nm":"Fill 1","hd":false},{"ty":"tr","p":{"a":0,"k":[0,0]},"a":{"a":0,"k":[0,0]},"s":{"a":0,"k":[100,100]},"r":{"a":0,"k":0},"o":{"a":0,"k":100},"sk":{"a":0,"k":0},"sa":{"a":0,"k":0},"nm":"Transform"}],"nm":"Group 1","bm":0,"hd":false}],"ip":0,"op":151,"st":0,"ct":1,"bm":0},{"ddd":0,"ind":9,"ty":4,"nm":"Layer 1 - Group 2","sr":1,"ks":{"o":{"a":0,"k":100},"r":{"k":[{"s":[9.011],"t":0,"i":{"x":[1],"y":[1]},"o":{"x":[0],"y":[0]}},{"s":[8.165],"t":1,"i":{"x":[1],"y":[1]},"o":{"x":[0],"y":[0]}},{"s":[7.293],"t":2,"i":{"x":[1],"y":[1]},"o":{"x":[0],"y":[0]}},{"s":[6.402],"t":3,"i":{"x":[1],"y":[1]},"o":{"x":[0],"y":[0]}},{"s":[5.496],"t":4,"i":{"x":[1],"y":[1]},"o":{"x":[0],"y":[0]}},{"s":[4.58],"t":5,"i":{"x":[1],"y":[1]},"o":{"x":[0],"y":[0]}},{"s":[3.658],"t":6,"i":{"x":[1],"y":[1]},"o":{"x":[0],"y":[0]}},{"s":[2.735],"t":7,"i":{"x":[1],"y":[1]},"o":{"x":[0],"y":[0]}},{"s":[1.816],"t":8,"i":{"x":[1],"y":[1]},"o":{"x":[0],"y":[0]}},{"s":[0.904],"t":9,"i":{"x":[1],"y":[1]},"o":{"x":[0],"y":[0]}},{"s":[0.004],"t":10,"i":{"x":[1],"y":[1]},"o":{"x":[0],"y":[0]}},{"s":[-0.881],"t":11,"i":{"x":[1],"y":[1]},"o":{"x":[0],"y":[0]}},{"s":[-1.745],"t":12,"i":{"x":[1],"y":[1]},"o":{"x":[0],"y":[0]}},{"s":[-2.587],"t":13,"i":{"x":[1],"y":[1]},"o":{"x":[0],"y":[0]}},{"s":[-3.404],"t":14,"i":{"x":[1],"y":[1]},"o":{"x":[0],"y":[0]}},{"s":[-4.199],"t":15,"i":{"x":[1],"y":[1]},"o":{"x":[0],"y":[0]}},{"s":[-4.968],"t":16,"i":{"x":[1],"y":[1]},"o":{"x":[0],"y":[0]}},{"s":[-5.71],"t":17,"i":{"x":[1],"y":[1]},"o":{"x":[0],"y":[0]}},{"s":[-6.421],"t":18,"i":{"x":[1],"y":[1]},"o":{"x":[0],"y":[0]}},{"s":[-7.098],"t":19,"i":{"x":[1],"y":[1]},"o":{"x":[0],"y":[0]}},{"s":[-7.738],"t":20,"i":{"x":[1],"y":[1]},"o":{"x":[0],"y":[0]}},{"s":[-8.338],"t":21,"i":{"x":[1],"y":[1]},"o":{"x":[0],"y":[0]}},{"s":[-8.894],"t":22,"i":{"x":[1],"y":[1]},"o":{"x":[0],"y":[0]}},{"s":[-9.403],"t":23,"i":{"x":[1],"y":[1]},"o":{"x":[0],"y":[0]}},{"s":[-9.862],"t":24,"i":{"x":[1],"y":[1]},"o":{"x":[0],"y":[0]}},{"s":[-10.267],"t":25,"i":{"x":[1],"y":[1]},"o":{"x":[0],"y":[0]}},{"s":[-10.616],"t":26,"i":{"x":[1],"y":[1]},"o":{"x":[0],"y":[0]}},{"s":[-10.905],"t":27,"i":{"x":[1],"y":[1]},"o":{"x":[0],"y":[0]}},{"s":[-11.131],"t":28,"i":{"x":[1],"y":[1]},"o":{"x":[0],"y":[0]}},{"s":[-11.29],"t":29,"i":{"x":[1],"y":[1]},"o":{"x":[0],"y":[0]}},{"s":[-11.38],"t":30,"i":{"x":[1],"y":[1]},"o":{"x":[0],"y":[0]}},{"s":[-11.398],"t":31,"i":{"x":[1],"y":[1]},"o":{"x":[0],"y":[0]}},{"s":[-11.371],"t":32,"i":{"x":[1],"y":[1]},"o":{"x":[0],"y":[0]}},{"s":[-11.373],"t":33,"i":{"x":[1],"y":[1]},"o":{"x":[0],"y":[0]}},{"s":[-11.404],"t":34,"i":{"x":[1],"y":[1]},"o":{"x":[0],"y":[0]}},{"s":[-11.458],"t":35,"i":{"x":[1],"y":[1]},"o":{"x":[0],"y":[0]}},{"s":[-11.533],"t":36,"i":{"x":[1],"y":[1]},"o":{"x":[0],"y":[0]}},{"s":[-11.624],"t":37,"i":{"x":[1],"y":[1]},"o":{"x":[0],"y":[0]}},{"s":[-11.727],"t":38,"i":{"x":[1],"y":[1]},"o":{"x":[0],"y":[0]}},{"s":[-11.839],"t":39,"i":{"x":[1],"y":[1]},"o":{"x":[0],"y":[0]}},{"s":[-11.957],"t":40,"i":{"x":[1],"y":[1]},"o":{"x":[0],"y":[0]}},{"s":[-12.077],"t":41,"i":{"x":[1],"y":[1]},"o":{"x":[0],"y":[0]}},{"s":[-12.196],"t":42,"i":{"x":[1],"y":[1]},"o":{"x":[0],"y":[0]}},{"s":[-12.311],"t":43,"i":{"x":[1],"y":[1]},"o":{"x":[0],"y":[0]}},{"s":[-12.418],"t":44,"i":{"x":[1],"y":[1]},"o":{"x":[0],"y":[0]}},{"s":[-12.517],"t":45,"i":{"x":[1],"y":[1]},"o":{"x":[0],"y":[0]}},{"s":[-12.603],"t":46,"i":{"x":[1],"y":[1]},"o":{"x":[0],"y":[0]}},{"s":[-12.674],"t":47,"i":{"x":[1],"y":[1]},"o":{"x":[0],"y":[0]}},{"s":[-12.728],"t":48,"i":{"x":[1],"y":[1]},"o":{"x":[0],"y":[0]}},{"s":[-12.763],"t":49,"i":{"x":[1],"y":[1]},"o":{"x":[0],"y":[0]}},{"s":[-12.764],"t":51,"i":{"x":[1],"y":[1]},"o":{"x":[0],"y":[0]}},{"s":[-12.728],"t":52,"i":{"x":[1],"y":[1]},"o":{"x":[0],"y":[0]}},{"s":[-12.663],"t":53,"i":{"x":[1],"y":[1]},"o":{"x":[0],"y":[0]}},{"s":[-12.57],"t":54,"i":{"x":[1],"y":[1]},"o":{"x":[0],"y":[0]}},{"s":[-12.444],"t":55,"i":{"x":[1],"y":[1]},"o":{"x":[0],"y":[0]}},{"s":[-12.286],"t":56,"i":{"x":[1],"y":[1]},"o":{"x":[0],"y":[0]}},{"s":[-12.094],"t":57,"i":{"x":[1],"y":[1]},"o":{"x":[0],"y":[0]}},{"s":[-11.865],"t":58,"i":{"x":[1],"y":[1]},"o":{"x":[0],"y":[0]}},{"s":[-11.599],"t":59,"i":{"x":[1],"y":[1]},"o":{"x":[0],"y":[0]}},{"s":[-11.294],"t":60,"i":{"x":[1],"y":[1]},"o":{"x":[0],"y":[0]}},{"s":[-10.949],"t":61,"i":{"x":[1],"y":[1]},"o":{"x":[0],"y":[0]}},{"s":[-10.561],"t":62,"i":{"x":[1],"y":[1]},"o":{"x":[0],"y":[0]}},{"s":[-10.131],"t":63,"i":{"x":[1],"y":[1]},"o":{"x":[0],"y":[0]}},{"s":[-9.657],"t":64,"i":{"x":[1],"y":[1]},"o":{"x":[0],"y":[0]}},{"s":[-9.138],"t":65,"i":{"x":[1],"y":[1]},"o":{"x":[0],"y":[0]}},{"s":[-8.572],"t":66,"i":{"x":[1],"y":[1]},"o":{"x":[0],"y":[0]}},{"s":[-7.958],"t":67,"i":{"x":[1],"y":[1]},"o":{"x":[0],"y":[0]}},{"s":[-7.296],"t":68,"i":{"x":[1],"y":[1]},"o":{"x":[0],"y":[0]}},{"s":[-6.583],"t":69,"i":{"x":[1],"y":[1]},"o":{"x":[0],"y":[0]}},{"s":[-5.82],"t":70,"i":{"x":[1],"y":[1]},"o":{"x":[0],"y":[0]}},{"s":[-5.004],"t":71,"i":{"x":[1],"y":[1]},"o":{"x":[0],"y":[0]}},{"s":[-4.136],"t":72,"i":{"x":[1],"y":[1]},"o":{"x":[0],"y":[0]}},{"s":[-3.213],"t":73,"i":{"x":[1],"y":[1]},"o":{"x":[0],"y":[0]}},{"s":[-2.25],"t":74,"i":{"x":[1],"y":[1]},"o":{"x":[0],"y":[0]}},{"s":[-1.289],"t":75,"i":{"x":[1],"y":[1]},"o":{"x":[0],"y":[0]}},{"s":[-0.337],"t":76,"i":{"x":[1],"y":[1]},"o":{"x":[0],"y":[0]}},{"s":[0.603],"t":77,"i":{"x":[1],"y":[1]},"o":{"x":[0],"y":[0]}},{"s":[1.524],"t":78,"i":{"x":[1],"y":[1]},"o":{"x":[0],"y":[0]}},{"s":[2.423],"t":79,"i":{"x":[1],"y":[1]},"o":{"x":[0],"y":[0]}},{"s":[3.295],"t":80,"i":{"x":[1],"y":[1]},"o":{"x":[0],"y":[0]}},{"s":[4.137],"t":81,"i":{"x":[1],"y":[1]},"o":{"x":[0],"y":[0]}},{"s":[4.943],"t":82,"i":{"x":[1],"y":[1]},"o":{"x":[0],"y":[0]}},{"s":[5.709],"t":83,"i":{"x":[1],"y":[1]},"o":{"x":[0],"y":[0]}},{"s":[6.433],"t":84,"i":{"x":[1],"y":[1]},"o":{"x":[0],"y":[0]}},{"s":[7.11],"t":85,"i":{"x":[1],"y":[1]},"o":{"x":[0],"y":[0]}},{"s":[7.736],"t":86,"i":{"x":[1],"y":[1]},"o":{"x":[0],"y":[0]}},{"s":[8.308],"t":87,"i":{"x":[1],"y":[1]},"o":{"x":[0],"y":[0]}},{"s":[8.823],"t":88,"i":{"x":[1],"y":[1]},"o":{"x":[0],"y":[0]}},{"s":[9.279],"t":89,"i":{"x":[1],"y":[1]},"o":{"x":[0],"y":[0]}},{"s":[9.672],"t":90,"i":{"x":[1],"y":[1]},"o":{"x":[0],"y":[0]}},{"s":[10.001],"t":91,"i":{"x":[1],"y":[1]},"o":{"x":[0],"y":[0]}},{"s":[10.26],"t":92,"i":{"x":[1],"y":[1]},"o":{"x":[0],"y":[0]}},{"s":[10.446],"t":93,"i":{"x":[1],"y":[1]},"o":{"x":[0],"y":[0]}},{"s":[10.559],"t":94,"i":{"x":[1],"y":[1]},"o":{"x":[0],"y":[0]}},{"s":[10.601],"t":95,"i":{"x":[1],"y":[1]},"o":{"x":[0],"y":[0]}},{"s":[10.573],"t":96,"i":{"x":[1],"y":[1]},"o":{"x":[0],"y":[0]}},{"s":[10.477],"t":97,"i":{"x":[1],"y":[1]},"o":{"x":[0],"y":[0]}},{"s":[10.313],"t":98,"i":{"x":[1],"y":[1]},"o":{"x":[0],"y":[0]}},{"s":[10.083],"t":99,"i":{"x":[1],"y":[1]},"o":{"x":[0],"y":[0]}},{"s":[9.788],"t":100,"i":{"x":[1],"y":[1]},"o":{"x":[0],"y":[0]}},{"s":[9.431],"t":101,"i":{"x":[1],"y":[1]},"o":{"x":[0],"y":[0]}}]},"p":{"k":[{"s":[1348.187,575.184,0],"t":1,"i":{"x":1,"y":1},"o":{"x":0,"y":0}},{"s":[1347.249,575.406,0],"t":2,"i":{"x":1,"y":1},"o":{"x":0,"y":0}},{"s":[1346.309,575.635,0],"t":3,"i":{"x":1,"y":1},"o":{"x":0,"y":0}},{"s":[1345.37,575.87,0],"t":4,"i":{"x":1,"y":1},"o":{"x":0,"y":0}},{"s":[1344.436,576.112,0],"t":5,"i":{"x":1,"y":1},"o":{"x":0,"y":0}},{"s":[1343.514,576.358,0],"t":6,"i":{"x":1,"y":1},"o":{"x":0,"y":0}},{"s":[1342.605,576.61,0],"t":7,"i":{"x":1,"y":1},"o":{"x":0,"y":0}},{"s":[1341.716,576.867,0],"t":8,"i":{"x":1,"y":1},"o":{"x":0,"y":0}},{"s":[1340.85,577.128,0],"t":9,"i":{"x":1,"y":1},"o":{"x":0,"y":0}},{"s":[1340.012,577.394,0],"t":10,"i":{"x":1,"y":1},"o":{"x":0,"y":0}},{"s":[1339.207,577.664,0],"t":11,"i":{"x":1,"y":1},"o":{"x":0,"y":0}},{"s":[1338.437,577.939,0],"t":12,"i":{"x":1,"y":1},"o":{"x":0,"y":0}},{"s":[1337.709,578.218,0],"t":13,"i":{"x":1,"y":1},"o":{"x":0,"y":0}},{"s":[1336.38,578.783,0],"t":15,"i":{"x":1,"y":1},"o":{"x":0,"y":0}},{"s":[1335.221,579.345,0],"t":17,"i":{"x":1,"y":1},"o":{"x":0,"y":0}},{"s":[1334.25,579.895,0],"t":19,"i":{"x":1,"y":1},"o":{"x":0,"y":0}},{"s":[1333.479,580.423,0],"t":21,"i":{"x":1,"y":1},"o":{"x":0,"y":0}},{"s":[1332.922,580.915,0],"t":23,"i":{"x":1,"y":1},"o":{"x":0,"y":0}},{"s":[1332.589,581.363,0],"t":25,"i":{"x":1,"y":1},"o":{"x":0,"y":0}},{"s":[1332.528,581.923,0],"t":28,"i":{"x":1,"y":1},"o":{"x":0,"y":0}},{"s":[1333.279,582.417,0],"t":32,"i":{"x":1,"y":1},"o":{"x":0,"y":0}},{"s":[1334.107,582.834,0],"t":35,"i":{"x":1,"y":1},"o":{"x":0,"y":0}},{"s":[1334.974,583.405,0],"t":38,"i":{"x":1,"y":1},"o":{"x":0,"y":0}},{"s":[1335.578,583.851,0],"t":40,"i":{"x":1,"y":1},"o":{"x":0,"y":0}},{"s":[1336.204,584.332,0],"t":42,"i":{"x":1,"y":1},"o":{"x":0,"y":0}},{"s":[1336.852,584.836,0],"t":44,"i":{"x":1,"y":1},"o":{"x":0,"y":0}},{"s":[1337.522,585.346,0],"t":46,"i":{"x":1,"y":1},"o":{"x":0,"y":0}},{"s":[1338.213,585.851,0],"t":48,"i":{"x":1,"y":1},"o":{"x":0,"y":0}},{"s":[1338.925,586.334,0],"t":50,"i":{"x":1,"y":1},"o":{"x":0,"y":0}},{"s":[1339.655,586.784,0],"t":52,"i":{"x":1,"y":1},"o":{"x":0,"y":0}},{"s":[1340.786,587.369,0],"t":55,"i":{"x":1,"y":1},"o":{"x":0,"y":0}},{"s":[1341.958,587.817,0],"t":58,"i":{"x":1,"y":1},"o":{"x":0,"y":0}},{"s":[1343.174,588.1,0],"t":61,"i":{"x":1,"y":1},"o":{"x":0,"y":0}},{"s":[1344.445,588.205,0],"t":64,"i":{"x":1,"y":1},"o":{"x":0,"y":0}},{"s":[1345.784,588.13,0],"t":67,"i":{"x":1,"y":1},"o":{"x":0,"y":0}},{"s":[1346.728,587.988,0],"t":69,"i":{"x":1,"y":1},"o":{"x":0,"y":0}},{"s":[1347.723,587.781,0],"t":71,"i":{"x":1,"y":1},"o":{"x":0,"y":0}},{"s":[1348.782,587.522,0],"t":73,"i":{"x":1,"y":1},"o":{"x":0,"y":0}},{"s":[1349.847,587.195,0],"t":75,"i":{"x":1,"y":1},"o":{"x":0,"y":0}},{"s":[1350.801,586.751,0],"t":77,"i":{"x":1,"y":1},"o":{"x":0,"y":0}},{"s":[1351.626,586.194,0],"t":79,"i":{"x":1,"y":1},"o":{"x":0,"y":0}},{"s":[1351.986,585.874,0],"t":80,"i":{"x":1,"y":1},"o":{"x":0,"y":0}},{"s":[1352.309,585.527,0],"t":81,"i":{"x":1,"y":1},"o":{"x":0,"y":0}},{"s":[1352.593,585.155,0],"t":82,"i":{"x":1,"y":1},"o":{"x":0,"y":0}},{"s":[1352.837,584.758,0],"t":83,"i":{"x":1,"y":1},"o":{"x":0,"y":0}},{"s":[1353.041,584.337,0],"t":84,"i":{"x":1,"y":1},"o":{"x":0,"y":0}},{"s":[1353.202,583.894,0],"t":85,"i":{"x":1,"y":1},"o":{"x":0,"y":0}},{"s":[1353.319,583.431,0],"t":86,"i":{"x":1,"y":1},"o":{"x":0,"y":0}},{"s":[1353.393,582.948,0],"t":87,"i":{"x":1,"y":1},"o":{"x":0,"y":0}},{"s":[1353.422,582.448,0],"t":88,"i":{"x":1,"y":1},"o":{"x":0,"y":0}},{"s":[1353.405,581.932,0],"t":89,"i":{"x":1,"y":1},"o":{"x":0,"y":0}},{"s":[1353.342,581.403,0],"t":90,"i":{"x":1,"y":1},"o":{"x":0,"y":0}},{"s":[1353.233,580.863,0],"t":91,"i":{"x":1,"y":1},"o":{"x":0,"y":0}},{"s":[1353.077,580.317,0],"t":92,"i":{"x":1,"y":1},"o":{"x":0,"y":0}},{"s":[1352.872,579.776,0],"t":93,"i":{"x":1,"y":1},"o":{"x":0,"y":0}},{"s":[1352.62,579.239,0],"t":94,"i":{"x":1,"y":1},"o":{"x":0,"y":0}},{"s":[1352.322,578.704,0],"t":95,"i":{"x":1,"y":1},"o":{"x":0,"y":0}},{"s":[1351.981,578.17,0],"t":96,"i":{"x":1,"y":1},"o":{"x":0,"y":0}},{"s":[1351.599,577.637,0],"t":97,"i":{"x":1,"y":1},"o":{"x":0,"y":0}},{"s":[1351.177,577.105,0],"t":98,"i":{"x":1,"y":1},"o":{"x":0,"y":0}},{"s":[1350.716,576.572,0],"t":99,"i":{"x":1,"y":1},"o":{"x":0,"y":0}},{"s":[1350.219,576.039,0],"t":100,"i":{"x":1,"y":1},"o":{"x":0,"y":0}}]},"a":{"a":0,"k":[530.835,-172.279,0]},"s":{"a":0,"k":[100,100,100]}},"ao":0,"shapes":[{"ty":"gr","it":[{"ind":0,"ty":"sh","ks":{"a":0,"k":{"i":[[8.28,4.476],[0,0],[-3.983,9.348],[-0.195,13.479],[0,0],[-10.837,0],[0,0],[0,-10.837],[0,0],[7.217,-14.232],[5.537,-6.853]],"o":[[0,0],[-8.939,-4.832],[5.923,-13.903],[0,0],[0,-10.837],[0,0],[10.837,0],[0,0],[0,12.546],[-4.406,8.688],[-5.915,7.321]],"v":[[510.84,-70.976],[510.84,-70.976],[502.151,-95.998],[511.329,-137.07],[511.329,-152.656],[530.952,-172.279],[541.484,-172.279],[561.107,-152.656],[561.107,-139.296],[550.281,-99.13],[535.368,-75.819]],"c":true}},"nm":"Path 1","hd":false},{"ty":"tr","p":{"a":0,"k":[530.835,-120.442]},"a":{"a":0,"k":[530.835,-120.442]},"s":{"a":0,"k":[100,100]},"r":{"a":0,"k":0},"o":{"a":0,"k":100},"sk":{"a":0,"k":0},"sa":{"a":0,"k":0},"nm":"Transform"}],"nm":"Group 2","bm":0,"hd":false},{"ty":"fl","c":{"a":0,"k":[0.274509803922,0.509803921569,0.925490255917,1]},"o":{"a":0,"k":100},"r":1,"bm":0,"nm":"Fill 1","hd":false}],"ip":0,"op":151,"st":0,"ct":1,"bm":0},{"ddd":0,"ind":10,"ty":4,"nm":"Layer 1 - Group 3","sr":1,"ks":{"o":{"a":0,"k":100},"r":{"k":[{"s":[-7.633],"t":0,"i":{"x":[1],"y":[1]},"o":{"x":[0],"y":[0]}},{"s":[-7.968],"t":1,"i":{"x":[1],"y":[1]},"o":{"x":[0],"y":[0]}},{"s":[-8.319],"t":2,"i":{"x":[1],"y":[1]},"o":{"x":[0],"y":[0]}},{"s":[-8.697],"t":3,"i":{"x":[1],"y":[1]},"o":{"x":[0],"y":[0]}},{"s":[-9.098],"t":4,"i":{"x":[1],"y":[1]},"o":{"x":[0],"y":[0]}},{"s":[-9.516],"t":5,"i":{"x":[1],"y":[1]},"o":{"x":[0],"y":[0]}},{"s":[-9.949],"t":6,"i":{"x":[1],"y":[1]},"o":{"x":[0],"y":[0]}},{"s":[-10.392],"t":7,"i":{"x":[1],"y":[1]},"o":{"x":[0],"y":[0]}},{"s":[-10.841],"t":8,"i":{"x":[1],"y":[1]},"o":{"x":[0],"y":[0]}},{"s":[-11.293],"t":9,"i":{"x":[1],"y":[1]},"o":{"x":[0],"y":[0]}},{"s":[-11.744],"t":10,"i":{"x":[1],"y":[1]},"o":{"x":[0],"y":[0]}},{"s":[-12.191],"t":11,"i":{"x":[1],"y":[1]},"o":{"x":[0],"y":[0]}},{"s":[-12.631],"t":12,"i":{"x":[1],"y":[1]},"o":{"x":[0],"y":[0]}},{"s":[-13.06],"t":13,"i":{"x":[1],"y":[1]},"o":{"x":[0],"y":[0]}},{"s":[-13.476],"t":14,"i":{"x":[1],"y":[1]},"o":{"x":[0],"y":[0]}},{"s":[-13.875],"t":15,"i":{"x":[1],"y":[1]},"o":{"x":[0],"y":[0]}},{"s":[-14.256],"t":16,"i":{"x":[1],"y":[1]},"o":{"x":[0],"y":[0]}},{"s":[-14.615],"t":17,"i":{"x":[1],"y":[1]},"o":{"x":[0],"y":[0]}},{"s":[-14.951],"t":18,"i":{"x":[1],"y":[1]},"o":{"x":[0],"y":[0]}},{"s":[-15.261],"t":19,"i":{"x":[1],"y":[1]},"o":{"x":[0],"y":[0]}},{"s":[-15.542],"t":20,"i":{"x":[1],"y":[1]},"o":{"x":[0],"y":[0]}},{"s":[-15.794],"t":21,"i":{"x":[1],"y":[1]},"o":{"x":[0],"y":[0]}},{"s":[-16.015],"t":22,"i":{"x":[1],"y":[1]},"o":{"x":[0],"y":[0]}},{"s":[-16.202],"t":23,"i":{"x":[1],"y":[1]},"o":{"x":[0],"y":[0]}},{"s":[-16.354],"t":24,"i":{"x":[1],"y":[1]},"o":{"x":[0],"y":[0]}},{"s":[-16.47],"t":25,"i":{"x":[1],"y":[1]},"o":{"x":[0],"y":[0]}},{"s":[-16.548],"t":26,"i":{"x":[1],"y":[1]},"o":{"x":[0],"y":[0]}},{"s":[-16.588],"t":27,"i":{"x":[1],"y":[1]},"o":{"x":[0],"y":[0]}},{"s":[-16.589],"t":28,"i":{"x":[1],"y":[1]},"o":{"x":[0],"y":[0]}},{"s":[-16.549],"t":29,"i":{"x":[1],"y":[1]},"o":{"x":[0],"y":[0]}},{"s":[-16.469],"t":30,"i":{"x":[1],"y":[1]},"o":{"x":[0],"y":[0]}},{"s":[-16.347],"t":31,"i":{"x":[1],"y":[1]},"o":{"x":[0],"y":[0]}},{"s":[-16.183],"t":32,"i":{"x":[1],"y":[1]},"o":{"x":[0],"y":[0]}},{"s":[-15.977],"t":33,"i":{"x":[1],"y":[1]},"o":{"x":[0],"y":[0]}},{"s":[-15.728],"t":34,"i":{"x":[1],"y":[1]},"o":{"x":[0],"y":[0]}},{"s":[-15.438],"t":35,"i":{"x":[1],"y":[1]},"o":{"x":[0],"y":[0]}},{"s":[-15.105],"t":36,"i":{"x":[1],"y":[1]},"o":{"x":[0],"y":[0]}},{"s":[-14.731],"t":37,"i":{"x":[1],"y":[1]},"o":{"x":[0],"y":[0]}},{"s":[-14.315],"t":38,"i":{"x":[1],"y":[1]},"o":{"x":[0],"y":[0]}},{"s":[-13.859],"t":39,"i":{"x":[1],"y":[1]},"o":{"x":[0],"y":[0]}},{"s":[-13.362],"t":40,"i":{"x":[1],"y":[1]},"o":{"x":[0],"y":[0]}},{"s":[-12.826],"t":41,"i":{"x":[1],"y":[1]},"o":{"x":[0],"y":[0]}},{"s":[-12.251],"t":42,"i":{"x":[1],"y":[1]},"o":{"x":[0],"y":[0]}},{"s":[-11.64],"t":43,"i":{"x":[1],"y":[1]},"o":{"x":[0],"y":[0]}},{"s":[-10.994],"t":44,"i":{"x":[1],"y":[1]},"o":{"x":[0],"y":[0]}},{"s":[-10.319],"t":45,"i":{"x":[1],"y":[1]},"o":{"x":[0],"y":[0]}},{"s":[-9.617],"t":46,"i":{"x":[1],"y":[1]},"o":{"x":[0],"y":[0]}},{"s":[-8.894],"t":47,"i":{"x":[1],"y":[1]},"o":{"x":[0],"y":[0]}},{"s":[-8.152],"t":48,"i":{"x":[1],"y":[1]},"o":{"x":[0],"y":[0]}},{"s":[-7.397],"t":49,"i":{"x":[1],"y":[1]},"o":{"x":[0],"y":[0]}},{"s":[-6.631],"t":50,"i":{"x":[1],"y":[1]},"o":{"x":[0],"y":[0]}},{"s":[-5.861],"t":51,"i":{"x":[1],"y":[1]},"o":{"x":[0],"y":[0]}},{"s":[-5.089],"t":52,"i":{"x":[1],"y":[1]},"o":{"x":[0],"y":[0]}},{"s":[-4.32],"t":53,"i":{"x":[1],"y":[1]},"o":{"x":[0],"y":[0]}},{"s":[-3.559],"t":54,"i":{"x":[1],"y":[1]},"o":{"x":[0],"y":[0]}},{"s":[-2.81],"t":55,"i":{"x":[1],"y":[1]},"o":{"x":[0],"y":[0]}},{"s":[-2.076],"t":56,"i":{"x":[1],"y":[1]},"o":{"x":[0],"y":[0]}},{"s":[-1.363],"t":57,"i":{"x":[1],"y":[1]},"o":{"x":[0],"y":[0]}},{"s":[-0.674],"t":58,"i":{"x":[1],"y":[1]},"o":{"x":[0],"y":[0]}},{"s":[-0.013],"t":59,"i":{"x":[1],"y":[1]},"o":{"x":[0],"y":[0]}},{"s":[0.615],"t":60,"i":{"x":[1],"y":[1]},"o":{"x":[0],"y":[0]}},{"s":[1.206],"t":61,"i":{"x":[1],"y":[1]},"o":{"x":[0],"y":[0]}},{"s":[1.745],"t":62,"i":{"x":[1],"y":[1]},"o":{"x":[0],"y":[0]}},{"s":[2.23],"t":63,"i":{"x":[1],"y":[1]},"o":{"x":[0],"y":[0]}},{"s":[2.664],"t":64,"i":{"x":[1],"y":[1]},"o":{"x":[0],"y":[0]}},{"s":[3.048],"t":65,"i":{"x":[1],"y":[1]},"o":{"x":[0],"y":[0]}},{"s":[3.384],"t":66,"i":{"x":[1],"y":[1]},"o":{"x":[0],"y":[0]}},{"s":[3.672],"t":67,"i":{"x":[1],"y":[1]},"o":{"x":[0],"y":[0]}},{"s":[3.915],"t":68,"i":{"x":[1],"y":[1]},"o":{"x":[0],"y":[0]}},{"s":[4.112],"t":69,"i":{"x":[1],"y":[1]},"o":{"x":[0],"y":[0]}},{"s":[4.265],"t":70,"i":{"x":[1],"y":[1]},"o":{"x":[0],"y":[0]}},{"s":[4.374],"t":71,"i":{"x":[1],"y":[1]},"o":{"x":[0],"y":[0]}},{"s":[4.439],"t":72,"i":{"x":[1],"y":[1]},"o":{"x":[0],"y":[0]}},{"s":[4.462],"t":73,"i":{"x":[1],"y":[1]},"o":{"x":[0],"y":[0]}},{"s":[4.443],"t":74,"i":{"x":[1],"y":[1]},"o":{"x":[0],"y":[0]}},{"s":[4.383],"t":75,"i":{"x":[1],"y":[1]},"o":{"x":[0],"y":[0]}},{"s":[4.281],"t":76,"i":{"x":[1],"y":[1]},"o":{"x":[0],"y":[0]}},{"s":[4.139],"t":77,"i":{"x":[1],"y":[1]},"o":{"x":[0],"y":[0]}},{"s":[3.956],"t":78,"i":{"x":[1],"y":[1]},"o":{"x":[0],"y":[0]}},{"s":[3.735],"t":79,"i":{"x":[1],"y":[1]},"o":{"x":[0],"y":[0]}},{"s":[3.475],"t":80,"i":{"x":[1],"y":[1]},"o":{"x":[0],"y":[0]}},{"s":[3.178],"t":81,"i":{"x":[1],"y":[1]},"o":{"x":[0],"y":[0]}},{"s":[2.844],"t":82,"i":{"x":[1],"y":[1]},"o":{"x":[0],"y":[0]}},{"s":[2.476],"t":83,"i":{"x":[1],"y":[1]},"o":{"x":[0],"y":[0]}},{"s":[2.073],"t":84,"i":{"x":[1],"y":[1]},"o":{"x":[0],"y":[0]}},{"s":[1.638],"t":85,"i":{"x":[1],"y":[1]},"o":{"x":[0],"y":[0]}},{"s":[1.173],"t":86,"i":{"x":[1],"y":[1]},"o":{"x":[0],"y":[0]}},{"s":[0.68],"t":87,"i":{"x":[1],"y":[1]},"o":{"x":[0],"y":[0]}},{"s":[0.161],"t":88,"i":{"x":[1],"y":[1]},"o":{"x":[0],"y":[0]}},{"s":[-0.381],"t":89,"i":{"x":[1],"y":[1]},"o":{"x":[0],"y":[0]}},{"s":[-0.943],"t":90,"i":{"x":[1],"y":[1]},"o":{"x":[0],"y":[0]}},{"s":[-1.522],"t":91,"i":{"x":[1],"y":[1]},"o":{"x":[0],"y":[0]}},{"s":[-2.114],"t":92,"i":{"x":[1],"y":[1]},"o":{"x":[0],"y":[0]}},{"s":[-2.715],"t":93,"i":{"x":[1],"y":[1]},"o":{"x":[0],"y":[0]}},{"s":[-3.925],"t":95,"i":{"x":[1],"y":[1]},"o":{"x":[0],"y":[0]}},{"s":[-4.524],"t":96,"i":{"x":[1],"y":[1]},"o":{"x":[0],"y":[0]}},{"s":[-5.111],"t":97,"i":{"x":[1],"y":[1]},"o":{"x":[0],"y":[0]}},{"s":[-5.681],"t":98,"i":{"x":[1],"y":[1]},"o":{"x":[0],"y":[0]}},{"s":[-6.225],"t":99,"i":{"x":[1],"y":[1]},"o":{"x":[0],"y":[0]}},{"s":[-6.738],"t":100,"i":{"x":[1],"y":[1]},"o":{"x":[0],"y":[0]}},{"s":[-7.21],"t":101,"i":{"x":[1],"y":[1]},"o":{"x":[0],"y":[0]}}]},"p":{"k":[{"s":[1271.272,572.63,0],"t":1,"i":{"x":1,"y":1},"o":{"x":0,"y":0}},{"s":[1271.145,572.967,0],"t":2,"i":{"x":1,"y":1},"o":{"x":0,"y":0}},{"s":[1270.991,573.284,0],"t":3,"i":{"x":1,"y":1},"o":{"x":0,"y":0}},{"s":[1270.814,573.586,0],"t":4,"i":{"x":1,"y":1},"o":{"x":0,"y":0}},{"s":[1270.616,573.877,0],"t":5,"i":{"x":1,"y":1},"o":{"x":0,"y":0}},{"s":[1270.172,574.439,0],"t":7,"i":{"x":1,"y":1},"o":{"x":0,"y":0}},{"s":[1269.685,574.998,0],"t":9,"i":{"x":1,"y":1},"o":{"x":0,"y":0}},{"s":[1269.176,575.572,0],"t":11,"i":{"x":1,"y":1},"o":{"x":0,"y":0}},{"s":[1268.919,575.869,0],"t":12,"i":{"x":1,"y":1},"o":{"x":0,"y":0}},{"s":[1268.664,576.177,0],"t":13,"i":{"x":1,"y":1},"o":{"x":0,"y":0}},{"s":[1268.413,576.494,0],"t":14,"i":{"x":1,"y":1},"o":{"x":0,"y":0}},{"s":[1268.167,576.824,0],"t":15,"i":{"x":1,"y":1},"o":{"x":0,"y":0}},{"s":[1267.929,577.165,0],"t":16,"i":{"x":1,"y":1},"o":{"x":0,"y":0}},{"s":[1267.701,577.52,0],"t":17,"i":{"x":1,"y":1},"o":{"x":0,"y":0}},{"s":[1267.483,577.887,0],"t":18,"i":{"x":1,"y":1},"o":{"x":0,"y":0}},{"s":[1267.278,578.268,0],"t":19,"i":{"x":1,"y":1},"o":{"x":0,"y":0}},{"s":[1267.087,578.661,0],"t":20,"i":{"x":1,"y":1},"o":{"x":0,"y":0}},{"s":[1266.911,579.068,0],"t":21,"i":{"x":1,"y":1},"o":{"x":0,"y":0}},{"s":[1266.751,579.488,0],"t":22,"i":{"x":1,"y":1},"o":{"x":0,"y":0}},{"s":[1266.608,579.919,0],"t":23,"i":{"x":1,"y":1},"o":{"x":0,"y":0}},{"s":[1266.483,580.363,0],"t":24,"i":{"x":1,"y":1},"o":{"x":0,"y":0}},{"s":[1266.377,580.817,0],"t":25,"i":{"x":1,"y":1},"o":{"x":0,"y":0}},{"s":[1266.291,581.282,0],"t":26,"i":{"x":1,"y":1},"o":{"x":0,"y":0}},{"s":[1266.225,581.756,0],"t":27,"i":{"x":1,"y":1},"o":{"x":0,"y":0}},{"s":[1266.181,582.238,0],"t":28,"i":{"x":1,"y":1},"o":{"x":0,"y":0}},{"s":[1266.157,582.729,0],"t":29,"i":{"x":1,"y":1},"o":{"x":0,"y":0}},{"s":[1266.155,583.227,0],"t":30,"i":{"x":1,"y":1},"o":{"x":0,"y":0}},{"s":[1266.175,583.73,0],"t":31,"i":{"x":1,"y":1},"o":{"x":0,"y":0}},{"s":[1266.218,584.239,0],"t":32,"i":{"x":1,"y":1},"o":{"x":0,"y":0}},{"s":[1266.282,584.752,0],"t":33,"i":{"x":1,"y":1},"o":{"x":0,"y":0}},{"s":[1266.369,585.269,0],"t":34,"i":{"x":1,"y":1},"o":{"x":0,"y":0}},{"s":[1266.479,585.788,0],"t":35,"i":{"x":1,"y":1},"o":{"x":0,"y":0}},{"s":[1266.61,586.31,0],"t":36,"i":{"x":1,"y":1},"o":{"x":0,"y":0}},{"s":[1266.764,586.834,0],"t":37,"i":{"x":1,"y":1},"o":{"x":0,"y":0}},{"s":[1266.94,587.359,0],"t":38,"i":{"x":1,"y":1},"o":{"x":0,"y":0}},{"s":[1267.137,587.885,0],"t":39,"i":{"x":1,"y":1},"o":{"x":0,"y":0}},{"s":[1267.356,588.412,0],"t":40,"i":{"x":1,"y":1},"o":{"x":0,"y":0}},{"s":[1267.595,588.939,0],"t":41,"i":{"x":1,"y":1},"o":{"x":0,"y":0}},{"s":[1267.855,589.468,0],"t":42,"i":{"x":1,"y":1},"o":{"x":0,"y":0}},{"s":[1268.135,589.994,0],"t":43,"i":{"x":1,"y":1},"o":{"x":0,"y":0}},{"s":[1268.43,590.495,0],"t":44,"i":{"x":1,"y":1},"o":{"x":0,"y":0}},{"s":[1268.741,590.963,0],"t":45,"i":{"x":1,"y":1},"o":{"x":0,"y":0}},{"s":[1269.063,591.398,0],"t":46,"i":{"x":1,"y":1},"o":{"x":0,"y":0}},{"s":[1269.397,591.796,0],"t":47,"i":{"x":1,"y":1},"o":{"x":0,"y":0}},{"s":[1269.739,592.157,0],"t":48,"i":{"x":1,"y":1},"o":{"x":0,"y":0}},{"s":[1270.089,592.479,0],"t":49,"i":{"x":1,"y":1},"o":{"x":0,"y":0}},{"s":[1270.803,592.997,0],"t":51,"i":{"x":1,"y":1},"o":{"x":0,"y":0}},{"s":[1271.882,593.444,0],"t":54,"i":{"x":1,"y":1},"o":{"x":0,"y":0}},{"s":[1272.923,593.47,0],"t":57,"i":{"x":1,"y":1},"o":{"x":0,"y":0}},{"s":[1273.88,593.058,0],"t":60,"i":{"x":1,"y":1},"o":{"x":0,"y":0}},{"s":[1274.42,592.575,0],"t":62,"i":{"x":1,"y":1},"o":{"x":0,"y":0}},{"s":[1274.814,592.019,0],"t":64,"i":{"x":1,"y":1},"o":{"x":0,"y":0}},{"s":[1274.964,591.709,0],"t":65,"i":{"x":1,"y":1},"o":{"x":0,"y":0}},{"s":[1275.085,591.377,0],"t":66,"i":{"x":1,"y":1},"o":{"x":0,"y":0}},{"s":[1275.181,591.021,0],"t":67,"i":{"x":1,"y":1},"o":{"x":0,"y":0}},{"s":[1275.253,590.64,0],"t":68,"i":{"x":1,"y":1},"o":{"x":0,"y":0}},{"s":[1275.305,590.234,0],"t":69,"i":{"x":1,"y":1},"o":{"x":0,"y":0}},{"s":[1275.337,589.802,0],"t":70,"i":{"x":1,"y":1},"o":{"x":0,"y":0}},{"s":[1275.351,589.346,0],"t":71,"i":{"x":1,"y":1},"o":{"x":0,"y":0}},{"s":[1275.349,588.866,0],"t":72,"i":{"x":1,"y":1},"o":{"x":0,"y":0}},{"s":[1275.333,588.363,0],"t":73,"i":{"x":1,"y":1},"o":{"x":0,"y":0}},{"s":[1275.302,587.837,0],"t":74,"i":{"x":1,"y":1},"o":{"x":0,"y":0}},{"s":[1275.259,587.291,0],"t":75,"i":{"x":1,"y":1},"o":{"x":0,"y":0}},{"s":[1275.204,586.725,0],"t":76,"i":{"x":1,"y":1},"o":{"x":0,"y":0}},{"s":[1275.138,586.142,0],"t":77,"i":{"x":1,"y":1},"o":{"x":0,"y":0}},{"s":[1275.062,585.544,0],"t":78,"i":{"x":1,"y":1},"o":{"x":0,"y":0}},{"s":[1274.976,584.932,0],"t":79,"i":{"x":1,"y":1},"o":{"x":0,"y":0}},{"s":[1274.88,584.309,0],"t":80,"i":{"x":1,"y":1},"o":{"x":0,"y":0}},{"s":[1274.776,583.677,0],"t":81,"i":{"x":1,"y":1},"o":{"x":0,"y":0}},{"s":[1274.663,583.039,0],"t":82,"i":{"x":1,"y":1},"o":{"x":0,"y":0}},{"s":[1274.541,582.396,0],"t":83,"i":{"x":1,"y":1},"o":{"x":0,"y":0}},{"s":[1274.412,581.752,0],"t":84,"i":{"x":1,"y":1},"o":{"x":0,"y":0}},{"s":[1274.276,581.108,0],"t":85,"i":{"x":1,"y":1},"o":{"x":0,"y":0}},{"s":[1274.132,580.468,0],"t":86,"i":{"x":1,"y":1},"o":{"x":0,"y":0}},{"s":[1273.981,579.833,0],"t":87,"i":{"x":1,"y":1},"o":{"x":0,"y":0}},{"s":[1273.825,579.207,0],"t":88,"i":{"x":1,"y":1},"o":{"x":0,"y":0}},{"s":[1273.662,578.591,0],"t":89,"i":{"x":1,"y":1},"o":{"x":0,"y":0}},{"s":[1273.493,577.987,0],"t":90,"i":{"x":1,"y":1},"o":{"x":0,"y":0}},{"s":[1273.32,577.397,0],"t":91,"i":{"x":1,"y":1},"o":{"x":0,"y":0}},{"s":[1273.142,576.825,0],"t":92,"i":{"x":1,"y":1},"o":{"x":0,"y":0}},{"s":[1272.961,576.27,0],"t":93,"i":{"x":1,"y":1},"o":{"x":0,"y":0}},{"s":[1272.778,575.735,0],"t":94,"i":{"x":1,"y":1},"o":{"x":0,"y":0}},{"s":[1272.593,575.221,0],"t":95,"i":{"x":1,"y":1},"o":{"x":0,"y":0}},{"s":[1272.407,574.729,0],"t":96,"i":{"x":1,"y":1},"o":{"x":0,"y":0}},{"s":[1272.223,574.261,0],"t":97,"i":{"x":1,"y":1},"o":{"x":0,"y":0}},{"s":[1272.041,573.815,0],"t":98,"i":{"x":1,"y":1},"o":{"x":0,"y":0}},{"s":[1271.864,573.394,0],"t":99,"i":{"x":1,"y":1},"o":{"x":0,"y":0}},{"s":[1271.692,572.997,0],"t":100,"i":{"x":1,"y":1},"o":{"x":0,"y":0}}]},"a":{"a":0,"k":[457.585,-172.279,0]},"s":{"a":0,"k":[100,100,100]}},"ao":0,"shapes":[{"ty":"gr","it":[{"ind":0,"ty":"sh","ks":{"a":0,"k":{"i":[[8.28,4.476],[0,0],[-3.983,9.348],[-0.195,13.479],[0,0],[-10.837,0],[0,0],[0,-10.837],[0,0],[7.217,-14.232],[5.537,-6.853]],"o":[[0,0],[-8.939,-4.832],[5.923,-13.903],[0,0],[0,-10.837],[0,0],[10.837,0],[0,0],[0,12.546],[-4.406,8.688],[-5.915,7.321]],"v":[[437.589,-70.976],[437.589,-70.976],[428.901,-95.998],[438.079,-137.07],[438.079,-152.656],[457.702,-172.279],[468.234,-172.279],[487.857,-152.656],[487.857,-139.296],[477.031,-99.13],[462.118,-75.819]],"c":true}},"nm":"Path 2","hd":false},{"ty":"tr","p":{"a":0,"k":[457.585,-120.442]},"a":{"a":0,"k":[457.585,-120.442]},"s":{"a":0,"k":[100,100]},"r":{"a":0,"k":0},"o":{"a":0,"k":100},"sk":{"a":0,"k":0},"sa":{"a":0,"k":0},"nm":"Transform"}],"nm":"Group 3","bm":0,"hd":false},{"ty":"fl","c":{"a":0,"k":[0.274509803922,0.509803921569,0.925490255917,1]},"o":{"a":0,"k":100},"r":1,"bm":0,"nm":"Fill 1","hd":false}],"ip":0,"op":151,"st":0,"ct":1,"bm":0},{"ddd":0,"ind":11,"ty":4,"nm":"M 3","parent":3,"sr":1,"ks":{"o":{"a":0,"k":100},"r":{"a":0,"k":0},"p":{"a":0,"k":[0,0,0]},"a":{"a":0,"k":[0,0,0]},"s":{"a":0,"k":[100,100,100]}},"ao":0,"shapes":[{"ty":"gr","it":[{"ind":0,"ty":"sh","ks":{"a":0,"k":{"i":[[0,-23.399],[0,0],[14.52,0],[0,0],[0,0],[0,0],[0,0],[0,23.4],[0,0],[-14.51,0],[0,0]],"o":[[0,0],[0,23.4],[0,0],[0,0],[0,0],[0,0],[-14.51,0],[0,0],[0,-23.399],[0,0],[14.52,0]],"v":[[317.59,-240.38],[317.59,109.32],[291.46,151.78],[219.92,151.78],[219.92,282.84],[117.89,151.78],[-291.26,151.78],[-317.59,109.32],[-317.59,-240.38],[-291.26,-282.84],[291.46,-282.84]],"c":true}},"nm":"Path 1","hd":false},{"ty":"fl","c":{"a":0,"k":[0.274509817362,0.509803950787,0.92549020052,1]},"o":{"a":0,"k":100},"r":1,"bm":0,"nm":"Fill 1","hd":false},{"ty":"tr","p":{"a":0,"k":[0,0]},"a":{"a":0,"k":[0,0]},"s":{"a":0,"k":[100,100]},"r":{"a":0,"k":0},"o":{"a":0,"k":100},"sk":{"a":0,"k":0},"sa":{"a":0,"k":0},"nm":"Transform"}],"nm":"Group 1","bm":0,"hd":false}],"ip":0,"op":151,"st":0,"ct":1,"bm":0}],"markers":[]}